{"version":2,"droids":[{"template":"ConstructionDroid","id":119,"position":[3648,2880],"rotation":0,"startpos":0},{"template":"ConstructionDroid","id":127,"position":[3648,3648],"rotation":0,"startpos":0},{"template":"ConstructionDroid","id":761,"position":[2752,22080],"rotation":0,"startpos":3},{"template":"ConstructionDroid","id":112,"position":[3520,2368],"rotation":0,"startpos":0},{"template":"ConstructionDroid","id":113,"position":[3648,2368],"rotation":0,"startpos":0},{"template":"ConstructionDroid","id":114,"position":[3520,2496],"rotation":0,"startpos":0},{"template":"ConstructionDroid","id":115,"position":[3648,2496],"rotation":0,"startpos":0},{"template":"ConstructionDroid","id":116,"position":[3520,2752],"rotation":0,"startpos":0},{"template":"ConstructionDroid","id":117,"position":[3648,2752],"rotation":0,"startpos":0},{"template":"ConstructionDroid","id":118,"position":[3520,2880],"rotation":0,"startpos":0},{"template":"ConstructionDroid","id":120,"position":[3520,3136],"rotation":0,"startpos":0},{"template":"ConstructionDroid","id":121,"position":[3648,3136],"rotation":0,"startpos":0},{"template":"ConstructionDroid","id":122,"position":[3520,3264],"rotation":0,"startpos":0},{"template":"ConstructionDroid","id":123,"position":[3648,3264],"rotation":0,"startpos":0},{"template":"ConstructionDroid","id":124,"position":[3520,3520],"rotation":0,"startpos":0},{"template":"ConstructionDroid","id":125,"position":[3648,3520],"rotation":0,"startpos":0},{"template":"ConstructionDroid","id":126,"position":[3520,3648],"rotation":0,"startpos":0},{"template":"ConstructionDroid","id":246,"position":[6848,2880],"rotation":0,"startpos":1},{"template":"ConstructionDroid","id":254,"position":[6848,3648],"rotation":0,"startpos":1},{"template":"ConstructionDroid","id":239,"position":[6720,2368],"rotation":0,"startpos":1},{"template":"ConstructionDroid","id":240,"position":[6848,2368],"rotation":0,"startpos":1},{"template":"ConstructionDroid","id":241,"position":[6720,2496],"rotation":0,"startpos":1},{"template":"ConstructionDroid","id":242,"position":[6848,2496],"rotation":0,"startpos":1},{"template":"ConstructionDroid","id":243,"position":[6720,2752],"rotation":0,"startpos":1},{"template":"ConstructionDroid","id":244,"position":[6848,2752],"rotation":0,"startpos":1},{"template":"ConstructionDroid","id":245,"position":[6720,2880],"rotation":0,"startpos":1},{"template":"ConstructionDroid","id":247,"position":[6720,3136],"rotation":0,"startpos":1},{"template":"ConstructionDroid","id":248,"position":[6848,3136],"rotation":0,"startpos":1},{"template":"ConstructionDroid","id":249,"position":[6720,3264],"rotation":0,"startpos":1},{"template":"ConstructionDroid","id":250,"position":[6848,3264],"rotation":0,"startpos":1},{"template":"ConstructionDroid","id":251,"position":[6720,3520],"rotation":0,"startpos":1},{"template":"ConstructionDroid","id":252,"position":[6848,3520],"rotation":0,"startpos":1},{"template":"ConstructionDroid","id":253,"position":[6720,3648],"rotation":0,"startpos":1},{"template":"ConstructionDroid","id":373,"position":[10048,2880],"rotation":0,"startpos":2},{"template":"ConstructionDroid","id":381,"position":[10048,3648],"rotation":0,"startpos":2},{"template":"ConstructionDroid","id":366,"position":[9920,2368],"rotation":0,"startpos":2},{"template":"ConstructionDroid","id":367,"position":[10048,2368],"rotation":0,"startpos":2},{"template":"ConstructionDroid","id":368,"position":[9920,2496],"rotation":0,"startpos":2},{"template":"ConstructionDroid","id":369,"position":[10048,2496],"rotation":0,"startpos":2},{"template":"ConstructionDroid","id":370,"position":[9920,2752],"rotation":0,"startpos":2},{"template":"ConstructionDroid","id":371,"position":[10048,2752],"rotation":0,"startpos":2},{"template":"ConstructionDroid","id":372,"position":[9920,2880],"rotation":0,"startpos":2},{"template":"ConstructionDroid","id":374,"position":[9920,3136],"rotation":0,"startpos":2},{"template":"ConstructionDroid","id":375,"position":[10048,3136],"rotation":0,"startpos":2},{"template":"ConstructionDroid","id":376,"position":[9920,3264],"rotation":0,"startpos":2},{"template":"ConstructionDroid","id":377,"position":[10048,3264],"rotation":0,"startpos":2},{"template":"ConstructionDroid","id":378,"position":[9920,3520],"rotation":0,"startpos":2},{"template":"ConstructionDroid","id":379,"position":[10048,3520],"rotation":0,"startpos":2},{"template":"ConstructionDroid","id":380,"position":[9920,3648],"rotation":0,"startpos":2},{"template":"ConstructionDroid","id":502,"position":[9024,22592],"rotation":0,"startpos":5},{"template":"ConstructionDroid","id":508,"position":[9024,22080],"rotation":0,"startpos":5},{"template":"ConstructionDroid","id":493,"position":[9152,23360],"rotation":0,"startpos":5},{"template":"ConstructionDroid","id":494,"position":[9024,23360],"rotation":0,"startpos":5},{"template":"ConstructionDroid","id":495,"position":[9152,23232],"rotation":0,"startpos":5},{"template":"ConstructionDroid","id":496,"position":[9024,23232],"rotation":0,"startpos":5},{"template":"ConstructionDroid","id":497,"position":[9152,22976],"rotation":0,"startpos":5},{"template":"ConstructionDroid","id":498,"position":[9024,22976],"rotation":0,"startpos":5},{"template":"ConstructionDroid","id":499,"position":[9152,22848],"rotation":0,"startpos":5},{"template":"ConstructionDroid","id":500,"position":[9024,22848],"rotation":0,"startpos":5},{"template":"ConstructionDroid","id":501,"position":[9152,22592],"rotation":0,"startpos":5},{"template":"ConstructionDroid","id":503,"position":[9152,22464],"rotation":0,"startpos":5},{"template":"ConstructionDroid","id":504,"position":[9024,22464],"rotation":0,"startpos":5},{"template":"ConstructionDroid","id":505,"position":[9152,22208],"rotation":0,"startpos":5},{"template":"ConstructionDroid","id":506,"position":[9024,22208],"rotation":0,"startpos":5},{"template":"ConstructionDroid","id":507,"position":[9152,22080],"rotation":0,"startpos":5},{"template":"ConstructionDroid","id":629,"position":[5824,22592],"rotation":0,"startpos":4},{"template":"ConstructionDroid","id":635,"position":[5824,22080],"rotation":0,"startpos":4},{"template":"ConstructionDroid","id":620,"position":[5952,23360],"rotation":0,"startpos":4},{"template":"ConstructionDroid","id":621,"position":[5824,23360],"rotation":0,"startpos":4},{"template":"ConstructionDroid","id":622,"position":[5952,23232],"rotation":0,"startpos":4},{"template":"ConstructionDroid","id":623,"position":[5824,23232],"rotation":0,"startpos":4},{"template":"ConstructionDroid","id":624,"position":[5952,22976],"rotation":0,"startpos":4},{"template":"ConstructionDroid","id":625,"position":[5824,22976],"rotation":0,"startpos":4},{"template":"ConstructionDroid","id":626,"position":[5952,22848],"rotation":0,"startpos":4},{"template":"ConstructionDroid","id":627,"position":[5824,22848],"rotation":0,"startpos":4},{"template":"ConstructionDroid","id":628,"position":[5952,22592],"rotation":0,"startpos":4},{"template":"ConstructionDroid","id":630,"position":[5952,22464],"rotation":0,"startpos":4},{"template":"ConstructionDroid","id":631,"position":[5824,22464],"rotation":0,"startpos":4},{"template":"ConstructionDroid","id":632,"position":[5952,22208],"rotation":0,"startpos":4},{"template":"ConstructionDroid","id":633,"position":[5824,22208],"rotation":0,"startpos":4},{"template":"ConstructionDroid","id":634,"position":[5952,22080],"rotation":0,"startpos":4},{"template":"ConstructionDroid","id":756,"position":[2624,22592],"rotation":0,"startpos":3},{"template":"ConstructionDroid","id":762,"position":[2624,22080],"rotation":0,"startpos":3},{"template":"ConstructionDroid","id":747,"position":[2752,23360],"rotation":0,"startpos":3},{"template":"ConstructionDroid","id":748,"position":[2624,23360],"rotation":0,"startpos":3},{"template":"ConstructionDroid","id":749,"position":[2752,23232],"rotation":0,"startpos":3},{"template":"ConstructionDroid","id":750,"position":[2624,23232],"rotation":0,"startpos":3},{"template":"ConstructionDroid","id":751,"position":[2752,22976],"rotation":0,"startpos":3},{"template":"ConstructionDroid","id":752,"position":[2624,22976],"rotation":0,"startpos":3},{"template":"ConstructionDroid","id":753,"position":[2752,22848],"rotation":0,"startpos":3},{"template":"ConstructionDroid","id":754,"position":[2624,22848],"rotation":0,"startpos":3},{"template":"ConstructionDroid","id":755,"position":[2752,22592],"rotation":0,"startpos":3},{"template":"ConstructionDroid","id":757,"position":[2752,22464],"rotation":0,"startpos":3},{"template":"ConstructionDroid","id":758,"position":[2624,22464],"rotation":0,"startpos":3},{"template":"ConstructionDroid","id":759,"position":[2752,22208],"rotation":0,"startpos":3},{"template":"ConstructionDroid","id":760,"position":[2624,22208],"rotation":0,"startpos":3}]}