{"version":2,"features":[{"name":"OilResource","id":71,"position":[25152,7744],"rotation":0},{"name":"OilResource","id":73,"position":[15424,7872],"rotation":0},{"name":"OilResource","id":72,"position":[15296,7488],"rotation":0},{"name":"OilResource","id":8,"position":[30144,13888],"rotation":0},{"name":"OilResource","id":9,"position":[28736,15040],"rotation":0},{"name":"OilResource","id":10,"position":[15808,14144],"rotation":0},{"name":"OilResource","id":11,"position":[18240,14400],"rotation":0},{"name":"OilResource","id":12,"position":[5056,14784],"rotation":0},{"name":"OilResource","id":13,"position":[832,14784],"rotation":0},{"name":"OilResource","id":14,"position":[2112,8640],"rotation":0},{"name":"OilResource","id":33,"position":[7616,8768],"rotation":0},{"name":"OilResource","id":16,"position":[6336,11456],"rotation":0},{"name":"OilResource","id":17,"position":[8384,11584],"rotation":0},{"name":"OilResource","id":18,"position":[17344,11712],"rotation":0},{"name":"OilResource","id":19,"position":[15552,10304],"rotation":0},{"name":"OilResource","id":20,"position":[11456,10176],"rotation":0},{"name":"OilResource","id":21,"position":[14528,9280],"rotation":0},{"name":"OilResource","id":22,"position":[27200,11968],"rotation":0},{"name":"OilResource","id":23,"position":[26816,10048],"rotation":0},{"name":"OilResource","id":24,"position":[25408,10304],"rotation":0},{"name":"OilResource","id":25,"position":[23360,10048],"rotation":0},{"name":"OilResource","id":26,"position":[21568,10688],"rotation":0},{"name":"OilResource","id":27,"position":[19648,11456],"rotation":0},{"name":"OilResource","id":28,"position":[20416,9024],"rotation":0},{"name":"OilResource","id":38,"position":[192,8896],"rotation":0},{"name":"OilResource","id":37,"position":[29888,7360],"rotation":0},{"name":"OilResource","id":39,"position":[4416,10176],"rotation":0},{"name":"OilResource","id":40,"position":[13632,8896],"rotation":0},{"name":"OilResource","id":70,"position":[20544,7872],"rotation":0},{"name":"OilResource","id":44,"position":[576,1472],"rotation":0},{"name":"OilResource","id":45,"position":[1984,320],"rotation":0},{"name":"OilResource","id":46,"position":[14912,1216],"rotation":0},{"name":"OilResource","id":47,"position":[12480,960],"rotation":0},{"name":"OilResource","id":48,"position":[25664,576],"rotation":0},{"name":"OilResource","id":49,"position":[29888,576],"rotation":0},{"name":"OilResource","id":50,"position":[28608,6720],"rotation":0},{"name":"OilResource","id":51,"position":[24384,3904],"rotation":0},{"name":"OilResource","id":52,"position":[22336,3776],"rotation":0},{"name":"OilResource","id":53,"position":[13376,3648],"rotation":0},{"name":"OilResource","id":54,"position":[15168,5056],"rotation":0},{"name":"OilResource","id":55,"position":[19264,5184],"rotation":0},{"name":"OilResource","id":56,"position":[16192,6080],"rotation":0},{"name":"OilResource","id":57,"position":[3520,3392],"rotation":0},{"name":"OilResource","id":58,"position":[3904,5312],"rotation":0},{"name":"OilResource","id":59,"position":[5312,5056],"rotation":0},{"name":"OilResource","id":60,"position":[7360,5312],"rotation":0},{"name":"OilResource","id":61,"position":[9152,4672],"rotation":0},{"name":"OilResource","id":62,"position":[11072,3904],"rotation":0},{"name":"OilResource","id":63,"position":[10304,6336],"rotation":0},{"name":"OilResource","id":64,"position":[23104,6592],"rotation":0},{"name":"OilResource","id":65,"position":[30528,6464],"rotation":0},{"name":"OilResource","id":66,"position":[26304,5184],"rotation":0},{"name":"OilResource","id":67,"position":[17088,6464],"rotation":0},{"name":"OilResource","id":68,"position":[5824,7616],"rotation":0},{"name":"OilResource","id":69,"position":[10176,7360],"rotation":0}]}