{"version":2,"structures":[{"name":"A0BaBaFactory","id":1,"position":[3584,8000],"rotation":32768,"player":"scavenger"},{"name":"A0ResourceExtractor","id":2,"position":[2112,19008],"rotation":0,"startpos":2},{"name":"AASite-QuadMg1","id":4,"position":[4928,7744],"rotation":32768,"player":"scavenger"},{"name":"AASite-QuadMg1","id":5,"position":[4544,7744],"rotation":32768,"player":"scavenger"},{"name":"AASite-QuadMg1","id":6,"position":[3904,7744],"rotation":32768,"player":"scavenger"},{"name":"AASite-QuadMg1","id":7,"position":[3520,7744],"rotation":32768,"player":"scavenger"},{"name":"A0ResourceExtractor","id":3,"position":[2240,18880],"rotation":0,"startpos":2},{"name":"A0ResourceExtractor","id":8,"position":[2496,18880],"rotation":0,"startpos":2},{"name":"A0ResourceExtractor","id":9,"position":[2496,19008],"rotation":0,"startpos":2},{"name":"A0ResourceExtractor","id":10,"position":[2624,19008],"rotation":0,"startpos":2},{"name":"A0ResourceExtractor","id":11,"position":[2624,18880],"rotation":0,"startpos":2},{"name":"A0ResourceExtractor","id":12,"position":[2880,18880],"rotation":0,"startpos":2},{"name":"A0ResourceExtractor","id":13,"position":[2880,19008],"rotation":0,"startpos":2},{"name":"Emplacement-Howitzer150","id":15,"position":[4544,9024],"rotation":32768,"player":"scavenger"},{"name":"Emplacement-Howitzer150","id":16,"position":[4544,8896],"rotation":32768,"player":"scavenger"},{"name":"P0-AASite-Laser","id":17,"position":[5184,7744],"rotation":32768,"player":"scavenger"},{"name":"P0-AASite-Laser","id":18,"position":[4288,7744],"rotation":32768,"player":"scavenger"},{"name":"A0ResourceExtractor","id":14,"position":[3008,19008],"rotation":0,"startpos":2},{"name":"P0-AASite-Laser","id":20,"position":[4160,7744],"rotation":32768,"player":"scavenger"},{"name":"P0-AASite-Laser","id":21,"position":[3520,8256],"rotation":32768,"player":"scavenger"},{"name":"P0-AASite-Laser","id":22,"position":[3520,8640],"rotation":32768,"player":"scavenger"},{"name":"P0-AASite-Laser","id":23,"position":[3520,9024],"rotation":32768,"player":"scavenger"},{"name":"A0ResourceExtractor","id":24,"position":[3264,19008],"rotation":0,"startpos":2},{"name":"A0ResourceExtractor","id":25,"position":[3264,18880],"rotation":0,"startpos":2},{"name":"A0CommandCentre","id":19,"position":[2176,18560],"rotation":0,"startpos":2},{"name":"A0ResourceExtractor","id":28,"position":[1856,18880],"rotation":0,"startpos":2},{"name":"A0ResourceExtractor","id":29,"position":[1088,19008],"rotation":0,"startpos":2},{"name":"A0ResourceExtractor","id":30,"position":[1344,18880],"rotation":0,"startpos":2},{"name":"A0ResourceExtractor","id":26,"position":[3392,18880],"rotation":0,"startpos":2},{"name":"A0ResourceExtractor","id":32,"position":[4032,18880],"rotation":0,"startpos":2},{"name":"A0ResourceExtractor","id":33,"position":[3392,19008],"rotation":0,"startpos":2},{"name":"A0ResourceExtractor","id":34,"position":[3648,18880],"rotation":0,"startpos":2},{"name":"A0ResourceExtractor","id":31,"position":[1344,19008],"rotation":0,"startpos":2},{"name":"A0ResourceExtractor","id":37,"position":[576,19008],"rotation":0,"startpos":2},{"name":"A0ResourceExtractor","id":35,"position":[3648,19008],"rotation":0,"startpos":2},{"name":"A0ResourceExtractor","id":38,"position":[960,18880],"rotation":0,"startpos":2},{"name":"A0ResourceExtractor","id":36,"position":[1088,18880],"rotation":0,"startpos":2},{"name":"A0ResourceExtractor","id":40,"position":[704,18880],"rotation":0,"startpos":2},{"name":"A0ResourceExtractor","id":27,"position":[2112,18880],"rotation":0,"startpos":2},{"name":"A0ResourceExtractor","id":39,"position":[3776,19008],"rotation":0,"startpos":2},{"name":"Emplacement-Howitzer150","id":46,"position":[4544,8768],"rotation":32768,"player":"scavenger"},{"name":"Emplacement-Howitzer150","id":47,"position":[4544,8640],"rotation":32768,"player":"scavenger"},{"name":"A0ResourceExtractor","id":45,"position":[4160,18880],"rotation":0,"startpos":2},{"name":"Emplacement-Howitzer150","id":49,"position":[4544,8512],"rotation":32768,"player":"scavenger"},{"name":"Emplacement-Howitzer150","id":50,"position":[4544,8384],"rotation":32768,"player":"scavenger"},{"name":"Emplacement-Howitzer150","id":51,"position":[4544,8256],"rotation":32768,"player":"scavenger"},{"name":"Emplacement-Howitzer150","id":52,"position":[3904,9024],"rotation":32768,"player":"scavenger"},{"name":"Emplacement-Howitzer150","id":53,"position":[3904,8896],"rotation":32768,"player":"scavenger"},{"name":"Emplacement-Howitzer150","id":54,"position":[3904,8768],"rotation":32768,"player":"scavenger"},{"name":"Emplacement-Howitzer150","id":55,"position":[3904,8640],"rotation":32768,"player":"scavenger"},{"name":"A0ResourceExtractor","id":41,"position":[1472,19008],"rotation":0,"startpos":2},{"name":"A0ResourceExtractor","id":56,"position":[1472,18880],"rotation":0,"startpos":2},{"name":"Emplacement-Howitzer150","id":58,"position":[3904,8512],"rotation":32768,"player":"scavenger"},{"name":"Emplacement-Howitzer150","id":59,"position":[3904,8384],"rotation":32768,"player":"scavenger"},{"name":"Emplacement-Howitzer150","id":60,"position":[3904,8256],"rotation":32768,"player":"scavenger"},{"name":"A0ResourceExtractor","id":57,"position":[1728,18880],"rotation":0,"startpos":2},{"name":"A0ResourceExtractor","id":44,"position":[3776,18880],"rotation":0,"startpos":2},{"name":"A0ResourceExtractor","id":61,"position":[1728,19008],"rotation":0,"startpos":2},{"name":"A0ResourceExtractor","id":42,"position":[960,19008],"rotation":0,"startpos":2},{"name":"A0ResourceExtractor","id":43,"position":[3008,18880],"rotation":0,"startpos":2},{"name":"A0ResourceExtractor","id":64,"position":[704,19008],"rotation":0,"startpos":2},{"name":"Sys-CB-Tower01","id":67,"position":[4544,11584],"rotation":0,"player":"scavenger"},{"name":"Sys-CB-Tower01","id":68,"position":[3904,11584],"rotation":0,"player":"scavenger"},{"name":"Sys-SensoTowerWS","id":69,"position":[4544,10304],"rotation":0,"player":"scavenger"},{"name":"Sys-SensoTowerWS","id":70,"position":[3904,10304],"rotation":0,"player":"scavenger"},{"name":"P0-AASite-Laser","id":71,"position":[5184,11840],"rotation":0,"player":"scavenger"},{"name":"P0-AASite-Laser","id":72,"position":[4288,11840],"rotation":0,"player":"scavenger"},{"name":"P0-AASite-Laser","id":73,"position":[4160,11840],"rotation":0,"player":"scavenger"},{"name":"P0-AASite-Laser","id":74,"position":[3520,10560],"rotation":0,"player":"scavenger"},{"name":"P0-AASite-Laser","id":75,"position":[3520,10944],"rotation":0,"player":"scavenger"},{"name":"P0-AASite-Laser","id":76,"position":[3520,11328],"rotation":0,"player":"scavenger"},{"name":"A0BaBaBunker","id":77,"position":[5184,12864],"rotation":0,"player":"scavenger"},{"name":"A0BaBaHorizontalWall","id":78,"position":[4800,12864],"rotation":32768,"player":"scavenger"},{"name":"A0BaBaHorizontalWall","id":79,"position":[4672,12864],"rotation":32768,"player":"scavenger"},{"name":"A0BaBaGunTower","id":80,"position":[4544,12864],"rotation":32768,"player":"scavenger"},{"name":"A0BaBaGunTower","id":81,"position":[4928,12864],"rotation":49152,"player":"scavenger"},{"name":"A0BaBaBunker","id":82,"position":[4288,12864],"rotation":32768,"player":"scavenger"},{"name":"A0BaBaBunker","id":83,"position":[4160,12864],"rotation":0,"player":"scavenger"},{"name":"A0BaBaHorizontalWall","id":84,"position":[3648,12864],"rotation":0,"player":"scavenger"},{"name":"A0BaBaHorizontalWall","id":85,"position":[3776,12864],"rotation":0,"player":"scavenger"},{"name":"A0BaBaGunTower","id":86,"position":[3904,12864],"rotation":0,"player":"scavenger"},{"name":"A0BaBaGunTower","id":87,"position":[3520,12864],"rotation":16384,"player":"scavenger"},{"name":"A0BaBaRocketPitAT","id":88,"position":[5184,12096],"rotation":0,"player":"scavenger"},{"name":"A0BaBaRocketPit","id":89,"position":[5184,12224],"rotation":0,"player":"scavenger"},{"name":"A0BaBaBunker","id":90,"position":[5184,12352],"rotation":0,"player":"scavenger"},{"name":"A0BaBaMortarPit","id":91,"position":[4800,12096],"rotation":32768,"player":"scavenger"},{"name":"A0BaBaMortarPit","id":92,"position":[4672,12096],"rotation":32768,"player":"scavenger"},{"name":"A0CannonTower","id":93,"position":[4800,12224],"rotation":32768,"player":"scavenger"},{"name":"A0BaBaFlameTower","id":94,"position":[4672,12224],"rotation":32768,"player":"scavenger"},{"name":"A0BaBaHorizontalWall","id":95,"position":[4800,12352],"rotation":32768,"player":"scavenger"},{"name":"A0BaBaHorizontalWall","id":96,"position":[4672,12352],"rotation":32768,"player":"scavenger"},{"name":"A0BaBaGunTower","id":97,"position":[4544,12352],"rotation":32768,"player":"scavenger"},{"name":"A0BaBaGunTowerEND","id":98,"position":[4544,12224],"rotation":16384,"player":"scavenger"},{"name":"A0BaBaGunTower","id":99,"position":[4928,12352],"rotation":49152,"player":"scavenger"},{"name":"A0BaBaGunTowerEND","id":100,"position":[4928,12224],"rotation":16384,"player":"scavenger"},{"name":"A0BaBaRocketPitAT","id":101,"position":[5184,12608],"rotation":0,"player":"scavenger"},{"name":"A0BaBaRocketPit","id":102,"position":[5184,12736],"rotation":0,"player":"scavenger"},{"name":"A0BaBaMortarPit","id":103,"position":[4800,12608],"rotation":32768,"player":"scavenger"},{"name":"A0BaBaMortarPit","id":104,"position":[4672,12608],"rotation":32768,"player":"scavenger"},{"name":"A0CannonTower","id":105,"position":[4800,12736],"rotation":32768,"player":"scavenger"},{"name":"A0BaBaFlameTower","id":106,"position":[4672,12736],"rotation":32768,"player":"scavenger"},{"name":"A0BaBaGunTowerEND","id":107,"position":[4544,12736],"rotation":16384,"player":"scavenger"},{"name":"A0BaBaGunTowerEND","id":108,"position":[4928,12736],"rotation":16384,"player":"scavenger"},{"name":"A0BaBaRocketPitAT","id":109,"position":[4288,12096],"rotation":32768,"player":"scavenger"},{"name":"A0BaBaRocketPit","id":110,"position":[4288,12224],"rotation":32768,"player":"scavenger"},{"name":"A0BaBaBunker","id":111,"position":[4288,12352],"rotation":32768,"player":"scavenger"},{"name":"A0BaBaMortarPit","id":112,"position":[3648,12096],"rotation":0,"player":"scavenger"},{"name":"A0BaBaMortarPit","id":113,"position":[3776,12096],"rotation":0,"player":"scavenger"},{"name":"A0BaBaRocketPitAT","id":114,"position":[4160,12096],"rotation":0,"player":"scavenger"},{"name":"A0BaBaRocketPit","id":115,"position":[4160,12224],"rotation":0,"player":"scavenger"},{"name":"A0BaBaBunker","id":116,"position":[4160,12352],"rotation":0,"player":"scavenger"},{"name":"A0CannonTower","id":117,"position":[3648,12224],"rotation":0,"player":"scavenger"},{"name":"A0BaBaFlameTower","id":118,"position":[3776,12224],"rotation":0,"player":"scavenger"},{"name":"A0BaBaHorizontalWall","id":119,"position":[3648,12352],"rotation":0,"player":"scavenger"},{"name":"A0BaBaHorizontalWall","id":120,"position":[3776,12352],"rotation":0,"player":"scavenger"},{"name":"A0BaBaGunTower","id":121,"position":[3904,12352],"rotation":0,"player":"scavenger"},{"name":"A0BaBaGunTowerEND","id":122,"position":[3904,12224],"rotation":49152,"player":"scavenger"},{"name":"A0BaBaGunTower","id":123,"position":[3520,12352],"rotation":16384,"player":"scavenger"},{"name":"A0BaBaGunTowerEND","id":124,"position":[3520,12224],"rotation":49152,"player":"scavenger"},{"name":"A0BaBaRocketPitAT","id":125,"position":[4288,12608],"rotation":32768,"player":"scavenger"},{"name":"A0BaBaRocketPit","id":126,"position":[4288,12736],"rotation":32768,"player":"scavenger"},{"name":"A0BaBaMortarPit","id":127,"position":[3648,12608],"rotation":0,"player":"scavenger"},{"name":"A0BaBaMortarPit","id":128,"position":[3776,12608],"rotation":0,"player":"scavenger"},{"name":"A0BaBaRocketPitAT","id":129,"position":[4160,12608],"rotation":0,"player":"scavenger"},{"name":"A0BaBaRocketPit","id":130,"position":[4160,12736],"rotation":0,"player":"scavenger"},{"name":"A0CannonTower","id":131,"position":[3648,12736],"rotation":0,"player":"scavenger"},{"name":"A0BaBaFlameTower","id":132,"position":[3776,12736],"rotation":0,"player":"scavenger"},{"name":"A0BaBaGunTowerEND","id":133,"position":[3904,12736],"rotation":49152,"player":"scavenger"},{"name":"A0BaBaGunTowerEND","id":134,"position":[3520,12736],"rotation":49152,"player":"scavenger"},{"name":"Emplacement-Howitzer150","id":135,"position":[4544,11200],"rotation":0,"player":"scavenger"},{"name":"Emplacement-Howitzer150","id":136,"position":[4544,11072],"rotation":0,"player":"scavenger"},{"name":"Emplacement-Howitzer150","id":137,"position":[4544,10944],"rotation":0,"player":"scavenger"},{"name":"Emplacement-Howitzer150","id":138,"position":[4544,10816],"rotation":0,"player":"scavenger"},{"name":"Emplacement-Howitzer150","id":139,"position":[4544,10688],"rotation":0,"player":"scavenger"},{"name":"Emplacement-Howitzer150","id":140,"position":[4544,10560],"rotation":0,"player":"scavenger"},{"name":"Emplacement-Howitzer150","id":141,"position":[3904,11328],"rotation":0,"player":"scavenger"},{"name":"Emplacement-Howitzer150","id":142,"position":[3904,11200],"rotation":0,"player":"scavenger"},{"name":"Emplacement-Howitzer150","id":143,"position":[3904,11072],"rotation":0,"player":"scavenger"},{"name":"Emplacement-Howitzer150","id":144,"position":[3904,10944],"rotation":0,"player":"scavenger"},{"name":"Emplacement-Howitzer150","id":145,"position":[3904,10816],"rotation":0,"player":"scavenger"},{"name":"Emplacement-Howitzer150","id":146,"position":[3904,10688],"rotation":0,"player":"scavenger"},{"name":"Emplacement-Howitzer150","id":147,"position":[3904,10560],"rotation":0,"player":"scavenger"},{"name":"Emplacement-Howitzer150","id":148,"position":[4544,11328],"rotation":0,"player":"scavenger"},{"name":"AASite-QuadMg1","id":149,"position":[3520,11840],"rotation":32768,"player":"scavenger"},{"name":"AASite-QuadMg1","id":150,"position":[3904,11840],"rotation":32768,"player":"scavenger"},{"name":"AASite-QuadMg1","id":151,"position":[4544,11840],"rotation":32768,"player":"scavenger"},{"name":"AASite-QuadMg1","id":152,"position":[4928,11840],"rotation":32768,"player":"scavenger"},{"name":"A0BaBaFactory","id":153,"position":[3584,11584],"rotation":0,"player":"scavenger"},{"name":"A0BaBaPowerGenerator","id":154,"position":[3904,9792],"rotation":16384,"player":"scavenger"},{"name":"A0BaBaPowerGenerator","id":155,"position":[3648,9664],"rotation":16384,"player":"scavenger"},{"name":"A0BaBaPowerGenerator","id":156,"position":[3648,10176],"rotation":16384,"player":"scavenger"},{"name":"A0BaBaPowerGenerator","id":157,"position":[3648,9408],"rotation":16384,"player":"scavenger"},{"name":"A0BaBaPowerGenerator","id":158,"position":[3648,9920],"rotation":16384,"player":"scavenger"},{"name":"A0ResourceExtractor","id":160,"position":[1088,704],"rotation":32768,"startpos":3},{"name":"A0ResourceExtractor","id":159,"position":[3264,576],"rotation":32768,"startpos":3},{"name":"A0ResourceExtractor","id":161,"position":[1344,576],"rotation":32768,"startpos":3},{"name":"A0ResourceExtractor","id":163,"position":[3648,704],"rotation":32768,"startpos":3},{"name":"A0ResourceExtractor","id":166,"position":[3648,576],"rotation":32768,"startpos":3},{"name":"A0ResourceExtractor","id":165,"position":[576,576],"rotation":32768,"startpos":3},{"name":"A0ResourceExtractor","id":168,"position":[704,576],"rotation":32768,"startpos":3},{"name":"A0ResourceExtractor","id":169,"position":[576,704],"rotation":32768,"startpos":3},{"name":"A0ResourceExtractor","id":164,"position":[1088,576],"rotation":32768,"startpos":3},{"name":"A0ResourceExtractor","id":170,"position":[960,576],"rotation":32768,"startpos":3},{"name":"A0ResourceExtractor","id":167,"position":[3776,576],"rotation":32768,"startpos":3},{"name":"A0ResourceExtractor","id":173,"position":[3776,704],"rotation":32768,"startpos":3},{"name":"A0ResourceExtractor","id":175,"position":[4160,704],"rotation":32768,"startpos":3},{"name":"A0ResourceExtractor","id":162,"position":[3008,704],"rotation":32768,"startpos":3},{"name":"A0ResourceExtractor","id":171,"position":[1344,704],"rotation":32768,"startpos":3},{"name":"A0ResourceExtractor","id":174,"position":[4032,704],"rotation":32768,"startpos":3},{"name":"A0ResourceExtractor","id":178,"position":[1728,576],"rotation":32768,"startpos":3},{"name":"A0ResourceExtractor","id":180,"position":[1472,576],"rotation":32768,"startpos":3},{"name":"A0CommandCentre","id":177,"position":[2560,1024],"rotation":32768,"startpos":3},{"name":"A0ResourceExtractor","id":182,"position":[2240,704],"rotation":32768,"startpos":3},{"name":"A0ResourceExtractor","id":183,"position":[3008,576],"rotation":32768,"startpos":3},{"name":"A0ResourceExtractor","id":184,"position":[2496,576],"rotation":32768,"startpos":3},{"name":"A0ResourceExtractor","id":185,"position":[2624,576],"rotation":32768,"startpos":3},{"name":"A0ResourceExtractor","id":181,"position":[1728,704],"rotation":32768,"startpos":3},{"name":"A0ResourceExtractor","id":187,"position":[1472,704],"rotation":32768,"startpos":3},{"name":"A0ResourceExtractor","id":186,"position":[2624,704],"rotation":32768,"startpos":3},{"name":"A0ResourceExtractor","id":189,"position":[2112,704],"rotation":32768,"startpos":3},{"name":"A0ResourceExtractor","id":190,"position":[2880,704],"rotation":32768,"startpos":3},{"name":"A0ResourceExtractor","id":191,"position":[2880,576],"rotation":32768,"startpos":3},{"name":"A0ResourceExtractor","id":172,"position":[960,704],"rotation":32768,"startpos":3},{"name":"A0ResourceExtractor","id":192,"position":[2240,576],"rotation":32768,"startpos":3},{"name":"A0ResourceExtractor","id":188,"position":[1856,704],"rotation":32768,"startpos":3},{"name":"A0ResourceExtractor","id":179,"position":[4032,576],"rotation":32768,"startpos":3},{"name":"A0ResourceExtractor","id":196,"position":[3392,576],"rotation":32768,"startpos":3},{"name":"A0ResourceExtractor","id":197,"position":[3392,704],"rotation":32768,"startpos":3},{"name":"A0ResourceExtractor","id":194,"position":[2112,576],"rotation":32768,"startpos":3},{"name":"A0BaBaRocketPit","id":200,"position":[4288,7360],"rotation":32768,"player":"scavenger"},{"name":"A0BaBaRocketPitAT","id":201,"position":[4288,7488],"rotation":32768,"player":"scavenger"},{"name":"A0BaBaMortarPit","id":202,"position":[4672,7488],"rotation":32768,"player":"scavenger"},{"name":"A0BaBaMortarPit","id":203,"position":[4800,7488],"rotation":32768,"player":"scavenger"},{"name":"A0BaBaGunTowerEND","id":204,"position":[3520,7360],"rotation":49152,"player":"scavenger"},{"name":"A0BaBaBunker","id":205,"position":[5184,7232],"rotation":0,"player":"scavenger"},{"name":"A0BaBaFlameTower","id":206,"position":[4672,7360],"rotation":32768,"player":"scavenger"},{"name":"A0BaBaHorizontalWall","id":207,"position":[4800,7232],"rotation":32768,"player":"scavenger"},{"name":"A0BaBaGunTowerEND","id":208,"position":[4928,7360],"rotation":16384,"player":"scavenger"},{"name":"A0BaBaRocketPitAT","id":209,"position":[5184,7488],"rotation":0,"player":"scavenger"},{"name":"A0BaBaRocketPit","id":210,"position":[5184,7360],"rotation":0,"player":"scavenger"},{"name":"A0CannonTower","id":211,"position":[3648,7360],"rotation":0,"player":"scavenger"},{"name":"A0BaBaFlameTower","id":212,"position":[3776,7360],"rotation":0,"player":"scavenger"},{"name":"A0BaBaHorizontalWall","id":213,"position":[3648,7232],"rotation":0,"player":"scavenger"},{"name":"A0BaBaHorizontalWall","id":214,"position":[3776,7232],"rotation":0,"player":"scavenger"},{"name":"A0BaBaGunTower","id":215,"position":[3904,7232],"rotation":0,"player":"scavenger"},{"name":"A0BaBaGunTowerEND","id":216,"position":[3904,7360],"rotation":49152,"player":"scavenger"},{"name":"A0BaBaGunTower","id":217,"position":[3520,7232],"rotation":16384,"player":"scavenger"},{"name":"A0BaBaBunker","id":218,"position":[4288,7232],"rotation":32768,"player":"scavenger"},{"name":"A0CannonTower","id":219,"position":[4800,7360],"rotation":32768,"player":"scavenger"},{"name":"A0BaBaMortarPit","id":220,"position":[3648,7488],"rotation":0,"player":"scavenger"},{"name":"A0BaBaMortarPit","id":221,"position":[3776,7488],"rotation":0,"player":"scavenger"},{"name":"A0BaBaRocketPitAT","id":222,"position":[4160,7488],"rotation":0,"player":"scavenger"},{"name":"A0BaBaRocketPit","id":223,"position":[4160,7360],"rotation":0,"player":"scavenger"},{"name":"A0BaBaBunker","id":224,"position":[4160,7232],"rotation":0,"player":"scavenger"},{"name":"A0BaBaHorizontalWall","id":225,"position":[4672,7232],"rotation":32768,"player":"scavenger"},{"name":"A0BaBaGunTower","id":226,"position":[4544,7232],"rotation":32768,"player":"scavenger"},{"name":"A0BaBaGunTowerEND","id":227,"position":[4544,7360],"rotation":16384,"player":"scavenger"},{"name":"A0BaBaGunTower","id":228,"position":[4928,7232],"rotation":49152,"player":"scavenger"},{"name":"Sys-SensoTowerWS","id":229,"position":[4544,9280],"rotation":32768,"player":"scavenger"},{"name":"Sys-SensoTowerWS","id":230,"position":[3904,9280],"rotation":32768,"player":"scavenger"},{"name":"Sys-CB-Tower01","id":231,"position":[4544,8000],"rotation":32768,"player":"scavenger"},{"name":"Sys-CB-Tower01","id":232,"position":[3904,8000],"rotation":32768,"player":"scavenger"},{"name":"A0BaBaGunTowerEND","id":233,"position":[3520,6848],"rotation":49152,"player":"scavenger"},{"name":"A0BaBaGunTower","id":234,"position":[3520,6720],"rotation":16384,"player":"scavenger"},{"name":"A0BaBaGunTowerEND","id":235,"position":[3904,6848],"rotation":49152,"player":"scavenger"},{"name":"A0BaBaGunTower","id":236,"position":[3904,6720],"rotation":0,"player":"scavenger"},{"name":"A0BaBaHorizontalWall","id":237,"position":[3776,6720],"rotation":0,"player":"scavenger"},{"name":"A0BaBaHorizontalWall","id":238,"position":[3648,6720],"rotation":0,"player":"scavenger"},{"name":"A0BaBaFlameTower","id":239,"position":[3776,6848],"rotation":0,"player":"scavenger"},{"name":"A0CannonTower","id":240,"position":[3648,6848],"rotation":0,"player":"scavenger"},{"name":"A0BaBaBunker","id":241,"position":[4160,6720],"rotation":0,"player":"scavenger"},{"name":"A0BaBaRocketPit","id":242,"position":[4160,6848],"rotation":0,"player":"scavenger"},{"name":"A0BaBaRocketPitAT","id":243,"position":[4160,6976],"rotation":0,"player":"scavenger"},{"name":"A0BaBaMortarPit","id":244,"position":[3776,6976],"rotation":0,"player":"scavenger"},{"name":"A0BaBaMortarPit","id":245,"position":[3648,6976],"rotation":0,"player":"scavenger"},{"name":"A0BaBaGunTowerEND","id":246,"position":[4928,6848],"rotation":16384,"player":"scavenger"},{"name":"A0BaBaGunTower","id":247,"position":[4928,6720],"rotation":49152,"player":"scavenger"},{"name":"A0BaBaGunTowerEND","id":248,"position":[4544,6848],"rotation":16384,"player":"scavenger"},{"name":"A0BaBaGunTower","id":249,"position":[4544,6720],"rotation":32768,"player":"scavenger"},{"name":"A0BaBaHorizontalWall","id":250,"position":[4672,6720],"rotation":32768,"player":"scavenger"},{"name":"A0BaBaHorizontalWall","id":251,"position":[4800,6720],"rotation":32768,"player":"scavenger"},{"name":"A0BaBaFlameTower","id":252,"position":[4672,6848],"rotation":32768,"player":"scavenger"},{"name":"A0CannonTower","id":253,"position":[4800,6848],"rotation":32768,"player":"scavenger"},{"name":"A0BaBaBunker","id":254,"position":[4288,6720],"rotation":32768,"player":"scavenger"},{"name":"A0BaBaRocketPit","id":255,"position":[4288,6848],"rotation":32768,"player":"scavenger"},{"name":"A0BaBaRocketPitAT","id":256,"position":[4288,6976],"rotation":32768,"player":"scavenger"},{"name":"A0BaBaMortarPit","id":257,"position":[4672,6976],"rotation":32768,"player":"scavenger"},{"name":"A0BaBaMortarPit","id":258,"position":[4800,6976],"rotation":32768,"player":"scavenger"},{"name":"A0BaBaBunker","id":259,"position":[5184,6720],"rotation":0,"player":"scavenger"},{"name":"A0BaBaRocketPit","id":260,"position":[5184,6848],"rotation":0,"player":"scavenger"},{"name":"A0BaBaRocketPitAT","id":261,"position":[5184,6976],"rotation":0,"player":"scavenger"},{"name":"A0ResourceExtractor","id":262,"position":[576,9920],"rotation":16384,"player":"scavenger"},{"name":"A0ResourceExtractor","id":263,"position":[576,10048],"rotation":16384,"player":"scavenger"},{"name":"A0ResourceExtractor","id":264,"position":[576,10176],"rotation":16384,"player":"scavenger"},{"name":"A0ResourceExtractor","id":265,"position":[576,10304],"rotation":16384,"player":"scavenger"},{"name":"A0ResourceExtractor","id":266,"position":[576,10432],"rotation":16384,"player":"scavenger"},{"name":"A0ResourceExtractor","id":267,"position":[576,10816],"rotation":16384,"player":"scavenger"},{"name":"A0ResourceExtractor","id":268,"position":[576,10688],"rotation":16384,"player":"scavenger"},{"name":"A0ResourceExtractor","id":269,"position":[576,10560],"rotation":16384,"player":"scavenger"},{"name":"A0ResourceExtractor","id":270,"position":[576,10944],"rotation":16384,"player":"scavenger"},{"name":"A0ResourceExtractor","id":271,"position":[576,11072],"rotation":16384,"player":"scavenger"},{"name":"A0ResourceExtractor","id":272,"position":[576,9664],"rotation":16384,"player":"scavenger"},{"name":"A0ResourceExtractor","id":273,"position":[576,9792],"rotation":16384,"player":"scavenger"},{"name":"A0ResourceExtractor","id":274,"position":[576,9536],"rotation":16384,"player":"scavenger"},{"name":"A0ResourceExtractor","id":275,"position":[576,9408],"rotation":16384,"player":"scavenger"},{"name":"A0ResourceExtractor","id":276,"position":[576,9280],"rotation":16384,"player":"scavenger"},{"name":"A0ResourceExtractor","id":277,"position":[576,9152],"rotation":16384,"player":"scavenger"},{"name":"A0ResourceExtractor","id":278,"position":[576,9024],"rotation":16384,"player":"scavenger"},{"name":"A0ResourceExtractor","id":279,"position":[576,8896],"rotation":16384,"player":"scavenger"},{"name":"A0ResourceExtractor","id":280,"position":[576,8768],"rotation":16384,"player":"scavenger"},{"name":"A0ResourceExtractor","id":281,"position":[576,8640],"rotation":16384,"player":"scavenger"},{"name":"A0ResourceExtractor","id":282,"position":[576,8512],"rotation":16384,"player":"scavenger"},{"name":"A0ResourceExtractor","id":65,"position":[2240,19008],"rotation":0,"startpos":2},{"name":"A0ResourceExtractor","id":66,"position":[576,18880],"rotation":0,"startpos":2},{"name":"A0ResourceExtractor","id":62,"position":[4032,19008],"rotation":0,"startpos":2},{"name":"A0ResourceExtractor","id":63,"position":[1856,19008],"rotation":0,"startpos":2},{"name":"A0ResourceExtractor","id":48,"position":[4160,19008],"rotation":0,"startpos":2},{"name":"A0ResourceExtractor","id":193,"position":[704,704],"rotation":32768,"startpos":3},{"name":"A0ResourceExtractor","id":195,"position":[1856,576],"rotation":32768,"startpos":3},{"name":"A0ResourceExtractor","id":199,"position":[2496,704],"rotation":32768,"startpos":3},{"name":"A0ResourceExtractor","id":198,"position":[3264,704],"rotation":32768,"startpos":3},{"name":"A0ResourceExtractor","id":176,"position":[4160,576],"rotation":32768,"startpos":3},{"name":"AASite-QuadMg1","id":394,"position":[6208,7744],"rotation":32768,"player":"scavenger"},{"name":"AASite-QuadMg1","id":395,"position":[5824,7744],"rotation":32768,"player":"scavenger"},{"name":"A0ResourceExtractor","id":396,"position":[6336,18880],"rotation":0,"startpos":1},{"name":"A0BaBaGunTowerEND","id":1366,"position":[6848,7360],"rotation":32768,"player":"scavenger"},{"name":"A0BaBaGunTowerEND","id":1367,"position":[7104,6720],"rotation":0,"player":"scavenger"},{"name":"AASite-QuadMg1","id":400,"position":[8256,7744],"rotation":0,"player":"scavenger"},{"name":"AASite-QuadMg1","id":401,"position":[8640,7744],"rotation":0,"player":"scavenger"},{"name":"A0ResourceExtractor","id":397,"position":[6592,18880],"rotation":0,"startpos":1},{"name":"A0CommandCentre","id":402,"position":[7040,18560],"rotation":0,"startpos":1},{"name":"Emplacement-Howitzer150","id":405,"position":[5824,8640],"rotation":32768,"player":"scavenger"},{"name":"Emplacement-Howitzer150","id":406,"position":[5824,8512],"rotation":32768,"player":"scavenger"},{"name":"Emplacement-Howitzer150","id":407,"position":[8256,8256],"rotation":32768,"player":"scavenger"},{"name":"Emplacement-Howitzer150","id":408,"position":[8256,8384],"rotation":32768,"player":"scavenger"},{"name":"Emplacement-Howitzer150","id":409,"position":[5824,8768],"rotation":32768,"player":"scavenger"},{"name":"Emplacement-Howitzer150","id":410,"position":[5824,8896],"rotation":32768,"player":"scavenger"},{"name":"A0ResourceExtractor","id":411,"position":[8256,19008],"rotation":0,"startpos":1},{"name":"A0ResourceExtractor","id":412,"position":[8640,18880],"rotation":0,"startpos":1},{"name":"A0ResourceExtractor","id":413,"position":[8896,18880],"rotation":0,"startpos":1},{"name":"A0ResourceExtractor","id":403,"position":[5440,18880],"rotation":0,"startpos":1},{"name":"A0ResourceExtractor","id":414,"position":[8896,19008],"rotation":0,"startpos":1},{"name":"A0ResourceExtractor","id":404,"position":[6592,19008],"rotation":0,"startpos":1},{"name":"A0ResourceExtractor","id":417,"position":[6720,19008],"rotation":0,"startpos":1},{"name":"A0ResourceExtractor","id":418,"position":[6720,18880],"rotation":0,"startpos":1},{"name":"A0ResourceExtractor","id":419,"position":[6976,18880],"rotation":0,"startpos":1},{"name":"P0-AASite-Laser","id":421,"position":[6592,7744],"rotation":32768,"player":"scavenger"},{"name":"P0-AASite-Laser","id":422,"position":[6464,7744],"rotation":32768,"player":"scavenger"},{"name":"P0-AASite-Laser","id":423,"position":[5568,7744],"rotation":32768,"player":"scavenger"},{"name":"P0-AASite-Laser","id":424,"position":[5440,7744],"rotation":32768,"player":"scavenger"},{"name":"A0ResourceExtractor","id":420,"position":[6976,19008],"rotation":0,"startpos":1},{"name":"A0ResourceExtractor","id":425,"position":[7104,19008],"rotation":0,"startpos":1},{"name":"A0ResourceExtractor","id":416,"position":[9024,19008],"rotation":0,"startpos":1},{"name":"A0ResourceExtractor","id":415,"position":[5568,19008],"rotation":0,"startpos":1},{"name":"A0ResourceExtractor","id":426,"position":[7104,18880],"rotation":0,"startpos":1},{"name":"A0ResourceExtractor","id":428,"position":[9024,18880],"rotation":0,"startpos":1},{"name":"A0ResourceExtractor","id":430,"position":[6208,19008],"rotation":0,"startpos":1},{"name":"A0ResourceExtractor","id":427,"position":[7360,18880],"rotation":0,"startpos":1},{"name":"Emplacement-Howitzer150","id":434,"position":[5824,8384],"rotation":32768,"player":"scavenger"},{"name":"Emplacement-Howitzer150","id":435,"position":[5824,8256],"rotation":32768,"player":"scavenger"},{"name":"A0ResourceExtractor","id":429,"position":[5568,18880],"rotation":0,"startpos":1},{"name":"A0ResourceExtractor","id":433,"position":[7360,19008],"rotation":0,"startpos":1},{"name":"A0ResourceExtractor","id":437,"position":[7488,19008],"rotation":0,"startpos":1},{"name":"A0ResourceExtractor","id":432,"position":[6336,19008],"rotation":0,"startpos":1},{"name":"A0ResourceExtractor","id":431,"position":[8512,19008],"rotation":0,"startpos":1},{"name":"A0ResourceExtractor","id":440,"position":[8512,18880],"rotation":0,"startpos":1},{"name":"A0ResourceExtractor","id":436,"position":[5440,19008],"rotation":0,"startpos":1},{"name":"A0ResourceExtractor","id":438,"position":[7488,18880],"rotation":0,"startpos":1},{"name":"A0ResourceExtractor","id":443,"position":[7744,18880],"rotation":0,"startpos":1},{"name":"A0ResourceExtractor","id":441,"position":[8256,18880],"rotation":0,"startpos":1},{"name":"A0ResourceExtractor","id":444,"position":[7744,19008],"rotation":0,"startpos":1},{"name":"A0ResourceExtractor","id":442,"position":[5952,18880],"rotation":0,"startpos":1},{"name":"A0ResourceExtractor","id":447,"position":[5824,18880],"rotation":0,"startpos":1},{"name":"A0ResourceExtractor","id":446,"position":[7872,19008],"rotation":0,"startpos":1},{"name":"Emplacement-Howitzer150","id":450,"position":[6208,9024],"rotation":32768,"player":"scavenger"},{"name":"Emplacement-Howitzer150","id":451,"position":[6208,8896],"rotation":32768,"player":"scavenger"},{"name":"Emplacement-Howitzer150","id":452,"position":[6208,8768],"rotation":32768,"player":"scavenger"},{"name":"Emplacement-Howitzer150","id":453,"position":[6208,8640],"rotation":32768,"player":"scavenger"},{"name":"Emplacement-Howitzer150","id":454,"position":[6208,8512],"rotation":32768,"player":"scavenger"},{"name":"Emplacement-Howitzer150","id":455,"position":[6208,8384],"rotation":32768,"player":"scavenger"},{"name":"Emplacement-Howitzer150","id":456,"position":[6208,8256],"rotation":32768,"player":"scavenger"},{"name":"Emplacement-Howitzer150","id":457,"position":[5824,9024],"rotation":32768,"player":"scavenger"},{"name":"A0ResourceExtractor","id":449,"position":[7872,18880],"rotation":0,"startpos":1},{"name":"A0ResourceExtractor","id":458,"position":[8128,18880],"rotation":0,"startpos":1},{"name":"Emplacement-Howitzer150","id":460,"position":[8640,9024],"rotation":32768,"player":"scavenger"},{"name":"Emplacement-Howitzer150","id":461,"position":[8640,8896],"rotation":32768,"player":"scavenger"},{"name":"Emplacement-Howitzer150","id":462,"position":[8640,8768],"rotation":32768,"player":"scavenger"},{"name":"Emplacement-Howitzer150","id":463,"position":[8640,8640],"rotation":32768,"player":"scavenger"},{"name":"Emplacement-Howitzer150","id":464,"position":[8640,8512],"rotation":32768,"player":"scavenger"},{"name":"Emplacement-Howitzer150","id":465,"position":[8640,8384],"rotation":32768,"player":"scavenger"},{"name":"Emplacement-Howitzer150","id":466,"position":[8640,8256],"rotation":32768,"player":"scavenger"},{"name":"Emplacement-Howitzer150","id":467,"position":[8256,9024],"rotation":32768,"player":"scavenger"},{"name":"Emplacement-Howitzer150","id":468,"position":[8256,8896],"rotation":32768,"player":"scavenger"},{"name":"Emplacement-Howitzer150","id":469,"position":[8256,8768],"rotation":32768,"player":"scavenger"},{"name":"Emplacement-Howitzer150","id":470,"position":[8256,8640],"rotation":32768,"player":"scavenger"},{"name":"Emplacement-Howitzer150","id":471,"position":[8256,8512],"rotation":32768,"player":"scavenger"},{"name":"A0ResourceExtractor","id":448,"position":[5824,19008],"rotation":0,"startpos":1},{"name":"A0BaBaRocketPit","id":473,"position":[9024,6848],"rotation":32768,"player":"scavenger"},{"name":"A0BaBaRocketPitAT","id":474,"position":[9024,6976],"rotation":32768,"player":"scavenger"},{"name":"A0BaBaRocketPit","id":475,"position":[8896,6848],"rotation":0,"player":"scavenger"},{"name":"A0BaBaRocketPitAT","id":476,"position":[8896,6976],"rotation":0,"player":"scavenger"},{"name":"A0BaBaBunker","id":477,"position":[9024,7232],"rotation":32768,"player":"scavenger"},{"name":"A0BaBaRocketPit","id":478,"position":[9024,7360],"rotation":32768,"player":"scavenger"},{"name":"A0BaBaRocketPitAT","id":479,"position":[9024,7488],"rotation":32768,"player":"scavenger"},{"name":"A0BaBaBunker","id":480,"position":[8896,7232],"rotation":0,"player":"scavenger"},{"name":"A0BaBaRocketPit","id":481,"position":[8896,7360],"rotation":0,"player":"scavenger"},{"name":"A0BaBaRocketPitAT","id":482,"position":[8896,7488],"rotation":0,"player":"scavenger"},{"name":"A0BaBaGunTowerEND","id":483,"position":[8256,6848],"rotation":49152,"player":"scavenger"},{"name":"A0BaBaGunTowerEND","id":484,"position":[8640,6848],"rotation":49152,"player":"scavenger"},{"name":"A0BaBaFlameTower","id":485,"position":[8512,6848],"rotation":0,"player":"scavenger"},{"name":"A0CannonTower","id":486,"position":[8384,6848],"rotation":0,"player":"scavenger"},{"name":"A0BaBaMortarPit","id":487,"position":[8512,6976],"rotation":0,"player":"scavenger"},{"name":"A0BaBaMortarPit","id":488,"position":[8384,6976],"rotation":0,"player":"scavenger"},{"name":"A0BaBaRocketPit","id":489,"position":[8000,6848],"rotation":32768,"player":"scavenger"},{"name":"A0BaBaRocketPitAT","id":490,"position":[8000,6976],"rotation":32768,"player":"scavenger"},{"name":"A0BaBaRocketPit","id":491,"position":[7872,6848],"rotation":0,"player":"scavenger"},{"name":"A0BaBaRocketPitAT","id":492,"position":[7872,6976],"rotation":0,"player":"scavenger"},{"name":"A0BaBaGunTowerEND","id":493,"position":[8256,7360],"rotation":49152,"player":"scavenger"},{"name":"A0BaBaGunTower","id":494,"position":[8256,7232],"rotation":16384,"player":"scavenger"},{"name":"A0BaBaGunTowerEND","id":495,"position":[8640,7360],"rotation":49152,"player":"scavenger"},{"name":"A0BaBaGunTower","id":496,"position":[8640,7232],"rotation":0,"player":"scavenger"},{"name":"A0BaBaHorizontalWall","id":497,"position":[8512,7232],"rotation":0,"player":"scavenger"},{"name":"A0BaBaHorizontalWall","id":498,"position":[8384,7232],"rotation":0,"player":"scavenger"},{"name":"A0BaBaFlameTower","id":499,"position":[8512,7360],"rotation":0,"player":"scavenger"},{"name":"A0CannonTower","id":500,"position":[8384,7360],"rotation":0,"player":"scavenger"},{"name":"A0BaBaMortarPit","id":501,"position":[8512,7488],"rotation":0,"player":"scavenger"},{"name":"A0BaBaMortarPit","id":502,"position":[8384,7488],"rotation":0,"player":"scavenger"},{"name":"A0BaBaBunker","id":503,"position":[8000,7232],"rotation":32768,"player":"scavenger"},{"name":"A0BaBaRocketPit","id":504,"position":[8000,7360],"rotation":32768,"player":"scavenger"},{"name":"A0BaBaRocketPitAT","id":505,"position":[8000,7488],"rotation":32768,"player":"scavenger"},{"name":"A0BaBaBunker","id":506,"position":[7872,7232],"rotation":0,"player":"scavenger"},{"name":"A0BaBaRocketPit","id":507,"position":[7872,7360],"rotation":0,"player":"scavenger"},{"name":"A0BaBaRocketPitAT","id":508,"position":[7872,7488],"rotation":0,"player":"scavenger"},{"name":"A0BaBaFactory","id":1383,"position":[7040,11456],"rotation":32768,"player":"scavenger"},{"name":"A0BaBaHorizontalWall","id":1384,"position":[6976,12864],"rotation":0,"player":"scavenger"},{"name":"A0BaBaFlameTower","id":1374,"position":[6848,7488],"rotation":32768,"player":"scavenger"},{"name":"A0CannonTower","id":1375,"position":[7104,7488],"rotation":32768,"player":"scavenger"},{"name":"AASite-QuadMg1","id":1376,"position":[7104,7744],"rotation":0,"player":"scavenger"},{"name":"A0BaBaHorizontalWall","id":1362,"position":[6976,6720],"rotation":32768,"player":"scavenger"},{"name":"A0BaBaGunTowerEND","id":1368,"position":[6848,7232],"rotation":32768,"player":"scavenger"},{"name":"A0BaBaFlameTower","id":1369,"position":[6848,6976],"rotation":32768,"player":"scavenger"},{"name":"A0BaBaGunTowerEND","id":1370,"position":[7104,7360],"rotation":0,"player":"scavenger"},{"name":"A0BaBaHorizontalWall","id":1371,"position":[6976,7232],"rotation":32768,"player":"scavenger"},{"name":"AASite-QuadMg1","id":1377,"position":[6848,7744],"rotation":0,"player":"scavenger"},{"name":"A0BaBaHorizontalWall","id":1372,"position":[6976,7360],"rotation":32768,"player":"scavenger"},{"name":"A0CannonTower","id":1378,"position":[7104,6976],"rotation":32768,"player":"scavenger"},{"name":"A0BaBaMortarPit","id":1373,"position":[6976,7488],"rotation":32768,"player":"scavenger"},{"name":"A0BaBaMortarPit","id":1379,"position":[6976,6976],"rotation":32768,"player":"scavenger"},{"name":"A0BaBaGunTower","id":542,"position":[8640,12864],"rotation":0,"player":"scavenger"},{"name":"A0BaBaGunTowerEND","id":543,"position":[8640,12736],"rotation":49152,"player":"scavenger"},{"name":"A0BaBaGunTower","id":544,"position":[8256,12864],"rotation":16384,"player":"scavenger"},{"name":"A0BaBaGunTowerEND","id":545,"position":[8256,12736],"rotation":49152,"player":"scavenger"},{"name":"A0BaBaRocketPitAT","id":546,"position":[9024,12608],"rotation":32768,"player":"scavenger"},{"name":"A0BaBaRocketPit","id":547,"position":[9024,12736],"rotation":32768,"player":"scavenger"},{"name":"A0BaBaBunker","id":548,"position":[9024,12864],"rotation":32768,"player":"scavenger"},{"name":"A0BaBaHorizontalWall","id":549,"position":[8384,12864],"rotation":0,"player":"scavenger"},{"name":"A0BaBaHorizontalWall","id":550,"position":[8512,12864],"rotation":0,"player":"scavenger"},{"name":"A0BaBaBunker","id":551,"position":[8000,12864],"rotation":32768,"player":"scavenger"},{"name":"A0BaBaMortarPit","id":552,"position":[8384,12608],"rotation":0,"player":"scavenger"},{"name":"A0BaBaMortarPit","id":553,"position":[8512,12608],"rotation":0,"player":"scavenger"},{"name":"A0BaBaRocketPitAT","id":554,"position":[8896,12608],"rotation":0,"player":"scavenger"},{"name":"A0BaBaRocketPit","id":555,"position":[8896,12736],"rotation":0,"player":"scavenger"},{"name":"A0BaBaBunker","id":556,"position":[8896,12864],"rotation":0,"player":"scavenger"},{"name":"A0CannonTower","id":557,"position":[8384,12736],"rotation":0,"player":"scavenger"},{"name":"A0BaBaFlameTower","id":558,"position":[8512,12736],"rotation":0,"player":"scavenger"},{"name":"A0BaBaRocketPitAT","id":559,"position":[7872,12608],"rotation":0,"player":"scavenger"},{"name":"A0BaBaRocketPit","id":561,"position":[7872,12736],"rotation":0,"player":"scavenger"},{"name":"A0BaBaBunker","id":562,"position":[7872,12864],"rotation":0,"player":"scavenger"},{"name":"A0BaBaRocketPitAT","id":563,"position":[8000,12608],"rotation":32768,"player":"scavenger"},{"name":"A0BaBaRocketPit","id":564,"position":[8000,12736],"rotation":32768,"player":"scavenger"},{"name":"A0BaBaRocketPitAT","id":565,"position":[7872,12096],"rotation":0,"player":"scavenger"},{"name":"A0BaBaRocketPit","id":566,"position":[7872,12224],"rotation":0,"player":"scavenger"},{"name":"A0BaBaRocketPit","id":567,"position":[8000,12224],"rotation":32768,"player":"scavenger"},{"name":"A0BaBaBunker","id":568,"position":[8000,12352],"rotation":32768,"player":"scavenger"},{"name":"A0BaBaMortarPit","id":569,"position":[8384,12096],"rotation":0,"player":"scavenger"},{"name":"A0BaBaMortarPit","id":570,"position":[8512,12096],"rotation":0,"player":"scavenger"},{"name":"A0BaBaRocketPitAT","id":571,"position":[8896,12096],"rotation":0,"player":"scavenger"},{"name":"A0BaBaRocketPit","id":572,"position":[8896,12224],"rotation":0,"player":"scavenger"},{"name":"A0BaBaBunker","id":573,"position":[8896,12352],"rotation":0,"player":"scavenger"},{"name":"A0CannonTower","id":574,"position":[8384,12224],"rotation":0,"player":"scavenger"},{"name":"A0BaBaBunker","id":575,"position":[7872,12352],"rotation":0,"player":"scavenger"},{"name":"A0BaBaRocketPitAT","id":576,"position":[8000,12096],"rotation":32768,"player":"scavenger"},{"name":"A0BaBaHorizontalWall","id":1399,"position":[6976,12736],"rotation":0,"player":"scavenger"},{"name":"A0BaBaFlameTower","id":578,"position":[8512,12224],"rotation":0,"player":"scavenger"},{"name":"A0BaBaHorizontalWall","id":579,"position":[8384,12352],"rotation":0,"player":"scavenger"},{"name":"A0BaBaHorizontalWall","id":580,"position":[8512,12352],"rotation":0,"player":"scavenger"},{"name":"A0BaBaGunTower","id":581,"position":[8640,12352],"rotation":0,"player":"scavenger"},{"name":"A0BaBaGunTowerEND","id":582,"position":[8640,12224],"rotation":49152,"player":"scavenger"},{"name":"A0BaBaGunTower","id":583,"position":[8256,12352],"rotation":16384,"player":"scavenger"},{"name":"A0BaBaGunTowerEND","id":584,"position":[8256,12224],"rotation":49152,"player":"scavenger"},{"name":"A0BaBaRocketPitAT","id":585,"position":[9024,12096],"rotation":32768,"player":"scavenger"},{"name":"A0BaBaRocketPit","id":586,"position":[9024,12224],"rotation":32768,"player":"scavenger"},{"name":"A0BaBaBunker","id":587,"position":[9024,12352],"rotation":32768,"player":"scavenger"},{"name":"P0-AASite-Laser","id":588,"position":[6592,11840],"rotation":0,"player":"scavenger"},{"name":"P0-AASite-Laser","id":589,"position":[6464,11840],"rotation":0,"player":"scavenger"},{"name":"P0-AASite-Laser","id":590,"position":[5568,11840],"rotation":0,"player":"scavenger"},{"name":"P0-AASite-Laser","id":591,"position":[5440,11840],"rotation":0,"player":"scavenger"},{"name":"A0BaBaGunTowerEND","id":1393,"position":[7104,12224],"rotation":0,"player":"scavenger"},{"name":"A0BaBaGunTowerEND","id":1394,"position":[6848,12352],"rotation":32768,"player":"scavenger"},{"name":"A0BaBaGunTowerEND","id":1400,"position":[6848,12736],"rotation":32768,"player":"scavenger"},{"name":"A0BaBaBunker","id":595,"position":[6592,12864],"rotation":32768,"player":"scavenger"},{"name":"A0BaBaBunker","id":596,"position":[6464,12864],"rotation":0,"player":"scavenger"},{"name":"A0BaBaHorizontalWall","id":597,"position":[6080,12864],"rotation":32768,"player":"scavenger"},{"name":"A0BaBaHorizontalWall","id":598,"position":[5952,12864],"rotation":32768,"player":"scavenger"},{"name":"A0BaBaGunTower","id":599,"position":[5824,12864],"rotation":32768,"player":"scavenger"},{"name":"A0BaBaGunTower","id":600,"position":[6208,12864],"rotation":49152,"player":"scavenger"},{"name":"A0BaBaBunker","id":601,"position":[5568,12864],"rotation":32768,"player":"scavenger"},{"name":"A0BaBaBunker","id":602,"position":[5440,12864],"rotation":0,"player":"scavenger"},{"name":"A0BaBaGunTowerEND","id":1385,"position":[6848,12864],"rotation":32768,"player":"scavenger"},{"name":"A0BaBaGunTowerEND","id":1386,"position":[7104,12864],"rotation":0,"player":"scavenger"},{"name":"A0CannonTower","id":1387,"position":[7104,12096],"rotation":0,"player":"scavenger"},{"name":"A0BaBaFlameTower","id":1388,"position":[6848,12096],"rotation":0,"player":"scavenger"},{"name":"A0BaBaGunTowerEND","id":1401,"position":[7104,12736],"rotation":0,"player":"scavenger"},{"name":"A0BaBaMortarPit","id":1389,"position":[6976,12096],"rotation":0,"player":"scavenger"},{"name":"A0BaBaHorizontalWall","id":1390,"position":[6976,12224],"rotation":0,"player":"scavenger"},{"name":"AASite-QuadMg1","id":1402,"position":[7104,11840],"rotation":0,"player":"scavenger"},{"name":"AASite-QuadMg1","id":1403,"position":[6848,11840],"rotation":0,"player":"scavenger"},{"name":"A0BaBaFactory","id":1404,"position":[7040,10176],"rotation":32768,"player":"scavenger"},{"name":"A0BaBaFactory","id":1405,"position":[7040,9408],"rotation":32768,"player":"scavenger"},{"name":"A0BaBaGunTowerEND","id":1395,"position":[7104,12352],"rotation":0,"player":"scavenger"},{"name":"A0CannonTower","id":1396,"position":[7104,12608],"rotation":0,"player":"scavenger"},{"name":"A0BaBaFactory","id":1381,"position":[7040,8128],"rotation":0,"player":"scavenger"},{"name":"A0BaBaHorizontalWall","id":1382,"position":[6976,6848],"rotation":32768,"player":"scavenger"},{"name":"A0BaBaRocketPitAT","id":618,"position":[6592,12096],"rotation":32768,"player":"scavenger"},{"name":"A0BaBaRocketPit","id":619,"position":[6592,12224],"rotation":32768,"player":"scavenger"},{"name":"A0BaBaBunker","id":620,"position":[6592,12352],"rotation":32768,"player":"scavenger"},{"name":"A0BaBaRocketPitAT","id":621,"position":[6464,12096],"rotation":0,"player":"scavenger"},{"name":"A0BaBaRocketPit","id":622,"position":[6464,12224],"rotation":0,"player":"scavenger"},{"name":"A0BaBaBunker","id":623,"position":[6464,12352],"rotation":0,"player":"scavenger"},{"name":"A0BaBaMortarPit","id":624,"position":[6080,12096],"rotation":32768,"player":"scavenger"},{"name":"A0BaBaMortarPit","id":625,"position":[5952,12096],"rotation":32768,"player":"scavenger"},{"name":"A0CannonTower","id":626,"position":[6080,12224],"rotation":32768,"player":"scavenger"},{"name":"A0BaBaFlameTower","id":627,"position":[5952,12224],"rotation":32768,"player":"scavenger"},{"name":"A0BaBaHorizontalWall","id":628,"position":[6080,12352],"rotation":32768,"player":"scavenger"},{"name":"A0BaBaHorizontalWall","id":629,"position":[5952,12352],"rotation":32768,"player":"scavenger"},{"name":"A0BaBaGunTower","id":630,"position":[5824,12352],"rotation":32768,"player":"scavenger"},{"name":"A0BaBaGunTowerEND","id":631,"position":[5824,12224],"rotation":16384,"player":"scavenger"},{"name":"A0BaBaGunTower","id":632,"position":[6208,12352],"rotation":49152,"player":"scavenger"},{"name":"A0BaBaGunTowerEND","id":633,"position":[6208,12224],"rotation":16384,"player":"scavenger"},{"name":"A0BaBaRocketPitAT","id":634,"position":[6592,12608],"rotation":32768,"player":"scavenger"},{"name":"A0BaBaRocketPit","id":635,"position":[6592,12736],"rotation":32768,"player":"scavenger"},{"name":"A0BaBaRocketPitAT","id":636,"position":[6464,12608],"rotation":0,"player":"scavenger"},{"name":"A0BaBaRocketPit","id":637,"position":[6464,12736],"rotation":0,"player":"scavenger"},{"name":"A0BaBaMortarPit","id":638,"position":[6080,12608],"rotation":32768,"player":"scavenger"},{"name":"A0BaBaMortarPit","id":639,"position":[5952,12608],"rotation":32768,"player":"scavenger"},{"name":"A0CannonTower","id":640,"position":[6080,12736],"rotation":32768,"player":"scavenger"},{"name":"A0BaBaFlameTower","id":641,"position":[5952,12736],"rotation":32768,"player":"scavenger"},{"name":"A0BaBaGunTowerEND","id":642,"position":[5824,12736],"rotation":16384,"player":"scavenger"},{"name":"A0BaBaGunTowerEND","id":643,"position":[6208,12736],"rotation":16384,"player":"scavenger"},{"name":"A0BaBaRocketPitAT","id":644,"position":[5568,12096],"rotation":32768,"player":"scavenger"},{"name":"A0BaBaRocketPit","id":645,"position":[5568,12224],"rotation":32768,"player":"scavenger"},{"name":"A0BaBaBunker","id":646,"position":[5568,12352],"rotation":32768,"player":"scavenger"},{"name":"A0BaBaRocketPitAT","id":647,"position":[5440,12096],"rotation":0,"player":"scavenger"},{"name":"A0BaBaRocketPit","id":648,"position":[5440,12224],"rotation":0,"player":"scavenger"},{"name":"A0BaBaBunker","id":649,"position":[5440,12352],"rotation":0,"player":"scavenger"},{"name":"A0BaBaRocketPitAT","id":650,"position":[5568,12608],"rotation":32768,"player":"scavenger"},{"name":"A0BaBaRocketPit","id":651,"position":[5568,12736],"rotation":32768,"player":"scavenger"},{"name":"A0BaBaRocketPitAT","id":652,"position":[5440,12608],"rotation":0,"player":"scavenger"},{"name":"A0BaBaRocketPit","id":653,"position":[5440,12736],"rotation":0,"player":"scavenger"},{"name":"Emplacement-Howitzer150","id":654,"position":[6208,11072],"rotation":0,"player":"scavenger"},{"name":"Emplacement-Howitzer150","id":655,"position":[6208,10944],"rotation":0,"player":"scavenger"},{"name":"Emplacement-Howitzer150","id":656,"position":[6208,10816],"rotation":0,"player":"scavenger"},{"name":"Emplacement-Howitzer150","id":657,"position":[6208,10688],"rotation":0,"player":"scavenger"},{"name":"Emplacement-Howitzer150","id":658,"position":[6208,10560],"rotation":0,"player":"scavenger"},{"name":"Emplacement-Howitzer150","id":659,"position":[5824,11328],"rotation":0,"player":"scavenger"},{"name":"Emplacement-Howitzer150","id":660,"position":[5824,11200],"rotation":0,"player":"scavenger"},{"name":"Emplacement-Howitzer150","id":661,"position":[5824,11072],"rotation":0,"player":"scavenger"},{"name":"Emplacement-Howitzer150","id":662,"position":[5824,10944],"rotation":0,"player":"scavenger"},{"name":"Emplacement-Howitzer150","id":663,"position":[5824,10816],"rotation":0,"player":"scavenger"},{"name":"Emplacement-Howitzer150","id":664,"position":[5824,10688],"rotation":0,"player":"scavenger"},{"name":"Emplacement-Howitzer150","id":665,"position":[5824,10560],"rotation":0,"player":"scavenger"},{"name":"Emplacement-Howitzer150","id":666,"position":[8640,10560],"rotation":0,"player":"scavenger"},{"name":"Emplacement-Howitzer150","id":667,"position":[8256,11328],"rotation":0,"player":"scavenger"},{"name":"Emplacement-Howitzer150","id":668,"position":[8256,11200],"rotation":0,"player":"scavenger"},{"name":"Emplacement-Howitzer150","id":669,"position":[8256,11072],"rotation":0,"player":"scavenger"},{"name":"Emplacement-Howitzer150","id":670,"position":[8256,10944],"rotation":0,"player":"scavenger"},{"name":"Emplacement-Howitzer150","id":671,"position":[8256,10816],"rotation":0,"player":"scavenger"},{"name":"Emplacement-Howitzer150","id":672,"position":[8256,10688],"rotation":0,"player":"scavenger"},{"name":"Emplacement-Howitzer150","id":673,"position":[8256,10560],"rotation":0,"player":"scavenger"},{"name":"Emplacement-Howitzer150","id":674,"position":[8640,11328],"rotation":0,"player":"scavenger"},{"name":"Emplacement-Howitzer150","id":675,"position":[8640,11200],"rotation":0,"player":"scavenger"},{"name":"P0-AASite-Laser","id":676,"position":[9024,11840],"rotation":0,"player":"scavenger"},{"name":"P0-AASite-Laser","id":677,"position":[8896,11840],"rotation":0,"player":"scavenger"},{"name":"P0-AASite-Laser","id":678,"position":[8000,11840],"rotation":0,"player":"scavenger"},{"name":"P0-AASite-Laser","id":679,"position":[7872,11840],"rotation":0,"player":"scavenger"},{"name":"Emplacement-Howitzer150","id":680,"position":[8640,10688],"rotation":0,"player":"scavenger"},{"name":"Emplacement-Howitzer150","id":681,"position":[8640,10816],"rotation":0,"player":"scavenger"},{"name":"Emplacement-Howitzer150","id":682,"position":[6208,11200],"rotation":0,"player":"scavenger"},{"name":"Emplacement-Howitzer150","id":683,"position":[6208,11328],"rotation":0,"player":"scavenger"},{"name":"Emplacement-Howitzer150","id":684,"position":[8640,11072],"rotation":0,"player":"scavenger"},{"name":"Emplacement-Howitzer150","id":685,"position":[8640,10944],"rotation":0,"player":"scavenger"},{"name":"AASite-QuadMg1","id":686,"position":[5824,11840],"rotation":32768,"player":"scavenger"},{"name":"AASite-QuadMg1","id":687,"position":[6208,11840],"rotation":32768,"player":"scavenger"},{"name":"A0BaBaHorizontalWall","id":1391,"position":[6976,12352],"rotation":0,"player":"scavenger"},{"name":"A0BaBaGunTowerEND","id":1392,"position":[6848,12224],"rotation":32768,"player":"scavenger"},{"name":"AASite-QuadMg1","id":690,"position":[8640,11840],"rotation":0,"player":"scavenger"},{"name":"AASite-QuadMg1","id":691,"position":[8256,11840],"rotation":0,"player":"scavenger"},{"name":"A0BaBaFlameTower","id":1397,"position":[6848,12608],"rotation":0,"player":"scavenger"},{"name":"A0BaBaMortarPit","id":1398,"position":[6976,12608],"rotation":0,"player":"scavenger"},{"name":"A0ResourceExtractor","id":698,"position":[8128,704],"rotation":32768,"startpos":4},{"name":"A0ResourceExtractor","id":699,"position":[7872,704],"rotation":32768,"startpos":4},{"name":"A0ResourceExtractor","id":701,"position":[9024,704],"rotation":32768,"startpos":4},{"name":"A0ResourceExtractor","id":703,"position":[5824,704],"rotation":32768,"startpos":4},{"name":"A0ResourceExtractor","id":704,"position":[9024,576],"rotation":32768,"startpos":4},{"name":"A0ResourceExtractor","id":705,"position":[5568,704],"rotation":32768,"startpos":4},{"name":"A0ResourceExtractor","id":702,"position":[7872,576],"rotation":32768,"startpos":4},{"name":"A0ResourceExtractor","id":708,"position":[7744,576],"rotation":32768,"startpos":4},{"name":"A0ResourceExtractor","id":709,"position":[7488,704],"rotation":32768,"startpos":4},{"name":"A0ResourceExtractor","id":707,"position":[5440,576],"rotation":32768,"startpos":4},{"name":"A0ResourceExtractor","id":710,"position":[7488,576],"rotation":32768,"startpos":4},{"name":"A0ResourceExtractor","id":712,"position":[7360,576],"rotation":32768,"startpos":4},{"name":"A0ResourceExtractor","id":700,"position":[6208,576],"rotation":32768,"startpos":4},{"name":"A0ResourceExtractor","id":711,"position":[5568,576],"rotation":32768,"startpos":4},{"name":"A0ResourceExtractor","id":713,"position":[7360,704],"rotation":32768,"startpos":4},{"name":"A0ResourceExtractor","id":706,"position":[8896,576],"rotation":32768,"startpos":4},{"name":"A0ResourceExtractor","id":715,"position":[5952,576],"rotation":32768,"startpos":4},{"name":"A0ResourceExtractor","id":716,"position":[7744,704],"rotation":32768,"startpos":4},{"name":"A0ResourceExtractor","id":714,"position":[7104,704],"rotation":32768,"startpos":4},{"name":"A0ResourceExtractor","id":717,"position":[8256,576],"rotation":32768,"startpos":4},{"name":"A0ResourceExtractor","id":720,"position":[7104,576],"rotation":32768,"startpos":4},{"name":"A0ResourceExtractor","id":722,"position":[6976,576],"rotation":32768,"startpos":4},{"name":"A0ResourceExtractor","id":721,"position":[8896,704],"rotation":32768,"startpos":4},{"name":"A0ResourceExtractor","id":718,"position":[5824,576],"rotation":32768,"startpos":4},{"name":"A0ResourceExtractor","id":723,"position":[6976,704],"rotation":32768,"startpos":4},{"name":"A0ResourceExtractor","id":726,"position":[6208,704],"rotation":32768,"startpos":4},{"name":"A0ResourceExtractor","id":727,"position":[6720,704],"rotation":32768,"startpos":4},{"name":"A0ResourceExtractor","id":725,"position":[5952,704],"rotation":32768,"startpos":4},{"name":"A0ResourceExtractor","id":728,"position":[6720,576],"rotation":32768,"startpos":4},{"name":"A0ResourceExtractor","id":724,"position":[8256,704],"rotation":32768,"startpos":4},{"name":"A0ResourceExtractor","id":731,"position":[8640,704],"rotation":32768,"startpos":4},{"name":"A0ResourceExtractor","id":730,"position":[6592,576],"rotation":32768,"startpos":4},{"name":"A0ResourceExtractor","id":732,"position":[8512,704],"rotation":32768,"startpos":4},{"name":"A0ResourceExtractor","id":733,"position":[6592,704],"rotation":32768,"startpos":4},{"name":"A0ResourceExtractor","id":735,"position":[6336,704],"rotation":32768,"startpos":4},{"name":"A0ResourceExtractor","id":734,"position":[8512,576],"rotation":32768,"startpos":4},{"name":"A0ResourceExtractor","id":719,"position":[8128,576],"rotation":32768,"startpos":4},{"name":"A0BaBaGunTower","id":757,"position":[5824,6720],"rotation":32768,"player":"scavenger"},{"name":"A0BaBaGunTowerEND","id":758,"position":[5824,6848],"rotation":16384,"player":"scavenger"},{"name":"A0BaBaGunTower","id":759,"position":[6208,6720],"rotation":49152,"player":"scavenger"},{"name":"A0BaBaGunTowerEND","id":760,"position":[6208,6848],"rotation":16384,"player":"scavenger"},{"name":"A0BaBaRocketPitAT","id":761,"position":[5440,6976],"rotation":0,"player":"scavenger"},{"name":"A0BaBaRocketPit","id":762,"position":[5440,6848],"rotation":0,"player":"scavenger"},{"name":"A0BaBaBunker","id":763,"position":[5440,6720],"rotation":0,"player":"scavenger"},{"name":"A0BaBaHorizontalWall","id":764,"position":[6080,6720],"rotation":32768,"player":"scavenger"},{"name":"A0BaBaHorizontalWall","id":765,"position":[5952,6720],"rotation":32768,"player":"scavenger"},{"name":"A0BaBaBunker","id":766,"position":[6464,6720],"rotation":0,"player":"scavenger"},{"name":"A0BaBaMortarPit","id":767,"position":[6080,6976],"rotation":32768,"player":"scavenger"},{"name":"A0BaBaMortarPit","id":768,"position":[5952,6976],"rotation":32768,"player":"scavenger"},{"name":"A0BaBaRocketPitAT","id":769,"position":[5568,6976],"rotation":32768,"player":"scavenger"},{"name":"A0BaBaRocketPit","id":770,"position":[5568,6848],"rotation":32768,"player":"scavenger"},{"name":"A0BaBaBunker","id":771,"position":[5568,6720],"rotation":32768,"player":"scavenger"},{"name":"A0CannonTower","id":772,"position":[6080,6848],"rotation":32768,"player":"scavenger"},{"name":"A0BaBaFlameTower","id":773,"position":[5952,6848],"rotation":32768,"player":"scavenger"},{"name":"A0BaBaRocketPitAT","id":774,"position":[6592,6976],"rotation":32768,"player":"scavenger"},{"name":"A0BaBaRocketPit","id":776,"position":[6592,6848],"rotation":32768,"player":"scavenger"},{"name":"A0BaBaBunker","id":777,"position":[6592,6720],"rotation":32768,"player":"scavenger"},{"name":"A0BaBaRocketPitAT","id":778,"position":[6464,6976],"rotation":0,"player":"scavenger"},{"name":"A0BaBaRocketPit","id":779,"position":[6464,6848],"rotation":0,"player":"scavenger"},{"name":"A0BaBaRocketPitAT","id":780,"position":[6592,7488],"rotation":32768,"player":"scavenger"},{"name":"A0BaBaRocketPit","id":781,"position":[6592,7360],"rotation":32768,"player":"scavenger"},{"name":"A0BaBaRocketPit","id":782,"position":[6464,7360],"rotation":0,"player":"scavenger"},{"name":"A0BaBaBunker","id":783,"position":[6464,7232],"rotation":0,"player":"scavenger"},{"name":"A0BaBaMortarPit","id":784,"position":[6080,7488],"rotation":32768,"player":"scavenger"},{"name":"A0BaBaMortarPit","id":785,"position":[5952,7488],"rotation":32768,"player":"scavenger"},{"name":"A0BaBaRocketPitAT","id":786,"position":[5568,7488],"rotation":32768,"player":"scavenger"},{"name":"A0BaBaRocketPit","id":787,"position":[5568,7360],"rotation":32768,"player":"scavenger"},{"name":"A0BaBaBunker","id":788,"position":[5568,7232],"rotation":32768,"player":"scavenger"},{"name":"A0CannonTower","id":789,"position":[6080,7360],"rotation":32768,"player":"scavenger"},{"name":"A0BaBaBunker","id":790,"position":[6592,7232],"rotation":32768,"player":"scavenger"},{"name":"A0BaBaRocketPitAT","id":791,"position":[6464,7488],"rotation":0,"player":"scavenger"},{"name":"A0BaBaGunTowerEND","id":1380,"position":[7104,7232],"rotation":0,"player":"scavenger"},{"name":"A0BaBaFlameTower","id":793,"position":[5952,7360],"rotation":32768,"player":"scavenger"},{"name":"A0BaBaHorizontalWall","id":794,"position":[6080,7232],"rotation":32768,"player":"scavenger"},{"name":"A0BaBaHorizontalWall","id":795,"position":[5952,7232],"rotation":32768,"player":"scavenger"},{"name":"A0BaBaGunTower","id":796,"position":[5824,7232],"rotation":32768,"player":"scavenger"},{"name":"A0BaBaGunTowerEND","id":797,"position":[5824,7360],"rotation":16384,"player":"scavenger"},{"name":"A0BaBaGunTower","id":798,"position":[6208,7232],"rotation":49152,"player":"scavenger"},{"name":"A0BaBaGunTowerEND","id":799,"position":[6208,7360],"rotation":16384,"player":"scavenger"},{"name":"A0BaBaRocketPitAT","id":800,"position":[5440,7488],"rotation":0,"player":"scavenger"},{"name":"A0BaBaRocketPit","id":801,"position":[5440,7360],"rotation":0,"player":"scavenger"},{"name":"A0BaBaBunker","id":802,"position":[5440,7232],"rotation":0,"player":"scavenger"},{"name":"P0-AASite-Laser","id":803,"position":[7872,7744],"rotation":32768,"player":"scavenger"},{"name":"P0-AASite-Laser","id":804,"position":[8000,7744],"rotation":32768,"player":"scavenger"},{"name":"P0-AASite-Laser","id":805,"position":[8896,7744],"rotation":32768,"player":"scavenger"},{"name":"P0-AASite-Laser","id":806,"position":[9024,7744],"rotation":32768,"player":"scavenger"},{"name":"A0BaBaGunTowerEND","id":1363,"position":[7104,6848],"rotation":0,"player":"scavenger"},{"name":"A0BaBaGunTowerEND","id":1364,"position":[6848,6720],"rotation":32768,"player":"scavenger"},{"name":"A0BaBaGunTowerEND","id":1365,"position":[6848,6848],"rotation":32768,"player":"scavenger"},{"name":"A0BaBaBunker","id":810,"position":[7872,6720],"rotation":0,"player":"scavenger"},{"name":"A0BaBaBunker","id":811,"position":[8000,6720],"rotation":32768,"player":"scavenger"},{"name":"A0BaBaHorizontalWall","id":812,"position":[8384,6720],"rotation":0,"player":"scavenger"},{"name":"A0BaBaHorizontalWall","id":813,"position":[8512,6720],"rotation":0,"player":"scavenger"},{"name":"A0BaBaGunTower","id":814,"position":[8640,6720],"rotation":0,"player":"scavenger"},{"name":"A0BaBaGunTower","id":815,"position":[8256,6720],"rotation":16384,"player":"scavenger"},{"name":"A0BaBaBunker","id":816,"position":[8896,6720],"rotation":0,"player":"scavenger"},{"name":"A0BaBaBunker","id":817,"position":[9024,6720],"rotation":32768,"player":"scavenger"},{"name":"A0ResourceExtractor","id":472,"position":[5952,19008],"rotation":0,"startpos":1},{"name":"A0ResourceExtractor","id":439,"position":[6208,18880],"rotation":0,"startpos":1},{"name":"A0ResourceExtractor","id":459,"position":[8128,19008],"rotation":0,"startpos":1},{"name":"A0ResourceExtractor","id":445,"position":[8640,19008],"rotation":0,"startpos":1},{"name":"A0ResourceExtractor","id":737,"position":[8640,576],"rotation":32768,"startpos":4},{"name":"A0CommandCentre","id":738,"position":[7424,1024],"rotation":32768,"startpos":4},{"name":"A0ResourceExtractor","id":736,"position":[6336,576],"rotation":32768,"startpos":4},{"name":"A0ResourceExtractor","id":729,"position":[5440,704],"rotation":32768,"startpos":4},{"name":"A0BaBaFactory","id":906,"position":[10880,8000],"rotation":32768,"player":"scavenger"},{"name":"A0ResourceExtractor","id":907,"position":[12608,19008],"rotation":0,"startpos":0},{"name":"A0ResourceExtractor","id":908,"position":[13376,18880],"rotation":0,"startpos":0},{"name":"A0BaBaGunTowerEND","id":1449,"position":[7616,12864],"rotation":0,"player":"scavenger"},{"name":"A0ResourceExtractor","id":909,"position":[13120,19008],"rotation":0,"startpos":0},{"name":"A0ResourceExtractor","id":911,"position":[13376,19008],"rotation":0,"startpos":0},{"name":"A0ResourceExtractor","id":912,"position":[10816,18880],"rotation":0,"startpos":0},{"name":"A0ResourceExtractor","id":915,"position":[10816,19008],"rotation":0,"startpos":0},{"name":"A0ResourceExtractor","id":914,"position":[13888,19008],"rotation":0,"startpos":0},{"name":"A0ResourceExtractor","id":917,"position":[13760,19008],"rotation":0,"startpos":0},{"name":"A0ResourceExtractor","id":918,"position":[13888,18880],"rotation":0,"startpos":0},{"name":"A0ResourceExtractor","id":919,"position":[13504,19008],"rotation":0,"startpos":0},{"name":"A0ResourceExtractor","id":916,"position":[10688,19008],"rotation":0,"startpos":0},{"name":"A0ResourceExtractor","id":921,"position":[10688,18880],"rotation":0,"startpos":0},{"name":"AASite-QuadMg1","id":923,"position":[9536,7744],"rotation":0,"player":"scavenger"},{"name":"AASite-QuadMg1","id":924,"position":[9920,7744],"rotation":0,"player":"scavenger"},{"name":"AASite-QuadMg1","id":925,"position":[10560,7744],"rotation":0,"player":"scavenger"},{"name":"AASite-QuadMg1","id":926,"position":[10944,7744],"rotation":0,"player":"scavenger"},{"name":"A0ResourceExtractor","id":922,"position":[10432,18880],"rotation":0,"startpos":0},{"name":"A0ResourceExtractor","id":927,"position":[10304,18880],"rotation":0,"startpos":0},{"name":"A0ResourceExtractor","id":910,"position":[11456,18880],"rotation":0,"startpos":0},{"name":"Emplacement-Howitzer150","id":930,"position":[9920,8256],"rotation":32768,"player":"scavenger"},{"name":"A0ResourceExtractor","id":920,"position":[13504,18880],"rotation":0,"startpos":0},{"name":"A0ResourceExtractor","id":913,"position":[13120,18880],"rotation":0,"startpos":0},{"name":"A0ResourceExtractor","id":928,"position":[10304,19008],"rotation":0,"startpos":0},{"name":"A0CommandCentre","id":929,"position":[11904,18560],"rotation":0,"startpos":0},{"name":"A0ResourceExtractor","id":932,"position":[12736,19008],"rotation":0,"startpos":0},{"name":"A0ResourceExtractor","id":935,"position":[12992,19008],"rotation":0,"startpos":0},{"name":"A0ResourceExtractor","id":934,"position":[12224,18880],"rotation":0,"startpos":0},{"name":"A0ResourceExtractor","id":937,"position":[11456,19008],"rotation":0,"startpos":0},{"name":"A0ResourceExtractor","id":938,"position":[11840,19008],"rotation":0,"startpos":0},{"name":"A0ResourceExtractor","id":939,"position":[11840,18880],"rotation":0,"startpos":0},{"name":"A0ResourceExtractor","id":936,"position":[12736,18880],"rotation":0,"startpos":0},{"name":"A0ResourceExtractor","id":941,"position":[12608,18880],"rotation":0,"startpos":0},{"name":"A0ResourceExtractor","id":940,"position":[11968,19008],"rotation":0,"startpos":0},{"name":"A0ResourceExtractor","id":942,"position":[12352,18880],"rotation":0,"startpos":0},{"name":"A0ResourceExtractor","id":943,"position":[11584,18880],"rotation":0,"startpos":0},{"name":"A0ResourceExtractor","id":944,"position":[12352,19008],"rotation":0,"startpos":0},{"name":"A0ResourceExtractor","id":945,"position":[12224,19008],"rotation":0,"startpos":0},{"name":"A0ResourceExtractor","id":947,"position":[11968,18880],"rotation":0,"startpos":0},{"name":"Emplacement-Howitzer150","id":949,"position":[10560,9024],"rotation":32768,"player":"scavenger"},{"name":"Emplacement-Howitzer150","id":950,"position":[10560,8896],"rotation":32768,"player":"scavenger"},{"name":"Emplacement-Howitzer150","id":951,"position":[10560,8768],"rotation":32768,"player":"scavenger"},{"name":"Emplacement-Howitzer150","id":952,"position":[10560,8640],"rotation":32768,"player":"scavenger"},{"name":"Emplacement-Howitzer150","id":953,"position":[10560,8512],"rotation":32768,"player":"scavenger"},{"name":"Emplacement-Howitzer150","id":954,"position":[10560,8384],"rotation":32768,"player":"scavenger"},{"name":"Emplacement-Howitzer150","id":955,"position":[10560,8256],"rotation":32768,"player":"scavenger"},{"name":"Emplacement-Howitzer150","id":956,"position":[9920,9024],"rotation":32768,"player":"scavenger"},{"name":"Emplacement-Howitzer150","id":957,"position":[9920,8896],"rotation":32768,"player":"scavenger"},{"name":"Emplacement-Howitzer150","id":958,"position":[9920,8768],"rotation":32768,"player":"scavenger"},{"name":"Emplacement-Howitzer150","id":959,"position":[9920,8640],"rotation":32768,"player":"scavenger"},{"name":"Emplacement-Howitzer150","id":960,"position":[9920,8512],"rotation":32768,"player":"scavenger"},{"name":"Emplacement-Howitzer150","id":961,"position":[9920,8384],"rotation":32768,"player":"scavenger"},{"name":"A0BaBaGunTowerEND","id":962,"position":[10944,6848],"rotation":16384,"player":"scavenger"},{"name":"A0BaBaGunTowerEND","id":963,"position":[10560,6848],"rotation":16384,"player":"scavenger"},{"name":"A0BaBaFlameTower","id":964,"position":[10688,6848],"rotation":32768,"player":"scavenger"},{"name":"A0CannonTower","id":965,"position":[10816,6848],"rotation":32768,"player":"scavenger"},{"name":"A0BaBaRocketPit","id":966,"position":[10304,6848],"rotation":32768,"player":"scavenger"},{"name":"A0BaBaRocketPitAT","id":967,"position":[10304,6976],"rotation":32768,"player":"scavenger"},{"name":"A0BaBaMortarPit","id":968,"position":[10688,6976],"rotation":32768,"player":"scavenger"},{"name":"A0BaBaMortarPit","id":969,"position":[10816,6976],"rotation":32768,"player":"scavenger"},{"name":"A0BaBaRocketPit","id":970,"position":[10176,6848],"rotation":0,"player":"scavenger"},{"name":"A0BaBaRocketPitAT","id":971,"position":[10176,6976],"rotation":0,"player":"scavenger"},{"name":"A0BaBaGunTowerEND","id":972,"position":[10944,7360],"rotation":16384,"player":"scavenger"},{"name":"A0BaBaGunTower","id":973,"position":[10944,7232],"rotation":49152,"player":"scavenger"},{"name":"A0BaBaGunTowerEND","id":974,"position":[10560,7360],"rotation":16384,"player":"scavenger"},{"name":"A0BaBaGunTower","id":975,"position":[10560,7232],"rotation":32768,"player":"scavenger"},{"name":"A0BaBaHorizontalWall","id":976,"position":[10688,7232],"rotation":32768,"player":"scavenger"},{"name":"A0BaBaHorizontalWall","id":977,"position":[10816,7232],"rotation":32768,"player":"scavenger"},{"name":"A0BaBaFlameTower","id":978,"position":[10688,7360],"rotation":32768,"player":"scavenger"},{"name":"A0CannonTower","id":979,"position":[10816,7360],"rotation":32768,"player":"scavenger"},{"name":"A0BaBaBunker","id":980,"position":[10304,7232],"rotation":32768,"player":"scavenger"},{"name":"A0BaBaRocketPit","id":981,"position":[10304,7360],"rotation":32768,"player":"scavenger"},{"name":"A0BaBaRocketPitAT","id":982,"position":[10304,7488],"rotation":32768,"player":"scavenger"},{"name":"A0BaBaMortarPit","id":983,"position":[10688,7488],"rotation":32768,"player":"scavenger"},{"name":"A0BaBaMortarPit","id":984,"position":[10816,7488],"rotation":32768,"player":"scavenger"},{"name":"A0BaBaBunker","id":985,"position":[10176,7232],"rotation":0,"player":"scavenger"},{"name":"A0BaBaRocketPit","id":986,"position":[10176,7360],"rotation":0,"player":"scavenger"},{"name":"A0BaBaRocketPitAT","id":987,"position":[10176,7488],"rotation":0,"player":"scavenger"},{"name":"A0BaBaGunTowerEND","id":988,"position":[9536,6848],"rotation":49152,"player":"scavenger"},{"name":"A0BaBaGunTowerEND","id":989,"position":[9920,6848],"rotation":49152,"player":"scavenger"},{"name":"A0BaBaFlameTower","id":990,"position":[9792,6848],"rotation":0,"player":"scavenger"},{"name":"A0CannonTower","id":991,"position":[9664,6848],"rotation":0,"player":"scavenger"},{"name":"A0BaBaMortarPit","id":992,"position":[9792,6976],"rotation":0,"player":"scavenger"},{"name":"A0BaBaMortarPit","id":993,"position":[9664,6976],"rotation":0,"player":"scavenger"},{"name":"A0BaBaRocketPit","id":994,"position":[9280,6848],"rotation":32768,"player":"scavenger"},{"name":"A0BaBaRocketPitAT","id":995,"position":[9280,6976],"rotation":32768,"player":"scavenger"},{"name":"A0BaBaGunTowerEND","id":996,"position":[9536,7360],"rotation":49152,"player":"scavenger"},{"name":"A0BaBaGunTower","id":997,"position":[9536,7232],"rotation":16384,"player":"scavenger"},{"name":"A0BaBaGunTowerEND","id":998,"position":[9920,7360],"rotation":49152,"player":"scavenger"},{"name":"A0BaBaGunTower","id":999,"position":[9920,7232],"rotation":0,"player":"scavenger"},{"name":"A0BaBaHorizontalWall","id":1000,"position":[9792,7232],"rotation":0,"player":"scavenger"},{"name":"A0BaBaHorizontalWall","id":1001,"position":[9664,7232],"rotation":0,"player":"scavenger"},{"name":"A0BaBaFlameTower","id":1002,"position":[9792,7360],"rotation":0,"player":"scavenger"},{"name":"A0CannonTower","id":1003,"position":[9664,7360],"rotation":0,"player":"scavenger"},{"name":"A0BaBaMortarPit","id":1004,"position":[9792,7488],"rotation":0,"player":"scavenger"},{"name":"A0BaBaMortarPit","id":1005,"position":[9664,7488],"rotation":0,"player":"scavenger"},{"name":"A0BaBaBunker","id":1006,"position":[9280,7232],"rotation":32768,"player":"scavenger"},{"name":"A0BaBaRocketPit","id":1007,"position":[9280,7360],"rotation":32768,"player":"scavenger"},{"name":"A0BaBaRocketPitAT","id":1008,"position":[9280,7488],"rotation":32768,"player":"scavenger"},{"name":"A0BaBaGunTower","id":1009,"position":[10944,6720],"rotation":49152,"player":"scavenger"},{"name":"A0BaBaGunTower","id":1010,"position":[10560,6720],"rotation":32768,"player":"scavenger"},{"name":"A0BaBaHorizontalWall","id":1011,"position":[10688,6720],"rotation":32768,"player":"scavenger"},{"name":"A0BaBaHorizontalWall","id":1012,"position":[10816,6720],"rotation":32768,"player":"scavenger"},{"name":"A0BaBaBunker","id":1013,"position":[10304,6720],"rotation":32768,"player":"scavenger"},{"name":"A0BaBaBunker","id":1014,"position":[10176,6720],"rotation":0,"player":"scavenger"},{"name":"A0BaBaGunTower","id":1015,"position":[9536,6720],"rotation":16384,"player":"scavenger"},{"name":"A0BaBaGunTower","id":1016,"position":[9920,6720],"rotation":0,"player":"scavenger"},{"name":"A0BaBaHorizontalWall","id":1017,"position":[9792,6720],"rotation":0,"player":"scavenger"},{"name":"A0BaBaHorizontalWall","id":1018,"position":[9664,6720],"rotation":0,"player":"scavenger"},{"name":"A0BaBaBunker","id":1019,"position":[9280,6720],"rotation":32768,"player":"scavenger"},{"name":"A0ResourceExtractor","id":933,"position":[10432,19008],"rotation":0,"startpos":0},{"name":"A0ResourceExtractor","id":1020,"position":[11072,19008],"rotation":0,"startpos":0},{"name":"A0ResourceExtractor","id":1021,"position":[11072,18880],"rotation":0,"startpos":0},{"name":"A0ResourceExtractor","id":1022,"position":[11200,18880],"rotation":0,"startpos":0},{"name":"A0BaBaRocketPit","id":1024,"position":[10176,12224],"rotation":0,"player":"scavenger"},{"name":"A0BaBaRocketPitAT","id":1025,"position":[10176,12096],"rotation":0,"player":"scavenger"},{"name":"A0BaBaMortarPit","id":1026,"position":[9792,12096],"rotation":0,"player":"scavenger"},{"name":"A0BaBaMortarPit","id":1027,"position":[9664,12096],"rotation":0,"player":"scavenger"},{"name":"A0BaBaGunTowerEND","id":1028,"position":[10944,12224],"rotation":16384,"player":"scavenger"},{"name":"A0BaBaBunker","id":1029,"position":[9280,12352],"rotation":32768,"player":"scavenger"},{"name":"A0BaBaFlameTower","id":1030,"position":[9792,12224],"rotation":0,"player":"scavenger"},{"name":"A0BaBaHorizontalWall","id":1031,"position":[9664,12352],"rotation":0,"player":"scavenger"},{"name":"A0BaBaGunTowerEND","id":1032,"position":[9536,12224],"rotation":49152,"player":"scavenger"},{"name":"A0BaBaRocketPitAT","id":1033,"position":[9280,12096],"rotation":32768,"player":"scavenger"},{"name":"A0BaBaRocketPit","id":1034,"position":[9280,12224],"rotation":32768,"player":"scavenger"},{"name":"A0CannonTower","id":1035,"position":[10816,12224],"rotation":32768,"player":"scavenger"},{"name":"A0BaBaFlameTower","id":1036,"position":[10688,12224],"rotation":32768,"player":"scavenger"},{"name":"A0BaBaHorizontalWall","id":1037,"position":[10816,12352],"rotation":32768,"player":"scavenger"},{"name":"A0BaBaHorizontalWall","id":1038,"position":[10688,12352],"rotation":32768,"player":"scavenger"},{"name":"A0BaBaGunTower","id":1039,"position":[10560,12352],"rotation":32768,"player":"scavenger"},{"name":"A0BaBaGunTowerEND","id":1040,"position":[10560,12224],"rotation":16384,"player":"scavenger"},{"name":"A0BaBaGunTower","id":1041,"position":[10944,12352],"rotation":49152,"player":"scavenger"},{"name":"A0BaBaBunker","id":1042,"position":[10176,12352],"rotation":0,"player":"scavenger"},{"name":"A0CannonTower","id":1043,"position":[9664,12224],"rotation":0,"player":"scavenger"},{"name":"A0BaBaMortarPit","id":1044,"position":[10816,12096],"rotation":32768,"player":"scavenger"},{"name":"A0BaBaMortarPit","id":1045,"position":[10688,12096],"rotation":32768,"player":"scavenger"},{"name":"A0BaBaRocketPitAT","id":1046,"position":[10304,12096],"rotation":32768,"player":"scavenger"},{"name":"A0BaBaRocketPit","id":1047,"position":[10304,12224],"rotation":32768,"player":"scavenger"},{"name":"A0BaBaBunker","id":1048,"position":[10304,12352],"rotation":32768,"player":"scavenger"},{"name":"A0BaBaHorizontalWall","id":1049,"position":[9792,12352],"rotation":0,"player":"scavenger"},{"name":"A0BaBaGunTower","id":1050,"position":[9920,12352],"rotation":0,"player":"scavenger"},{"name":"A0BaBaGunTowerEND","id":1051,"position":[9920,12224],"rotation":49152,"player":"scavenger"},{"name":"A0BaBaGunTower","id":1052,"position":[9536,12352],"rotation":16384,"player":"scavenger"},{"name":"Sys-SensoTowerWS","id":1053,"position":[9920,10304],"rotation":0,"player":"scavenger"},{"name":"Sys-SensoTowerWS","id":1054,"position":[10560,10304],"rotation":0,"player":"scavenger"},{"name":"Sys-CB-Tower01","id":1055,"position":[9920,11584],"rotation":0,"player":"scavenger"},{"name":"Sys-CB-Tower01","id":1056,"position":[10560,11584],"rotation":0,"player":"scavenger"},{"name":"A0BaBaGunTowerEND","id":1057,"position":[10944,12736],"rotation":16384,"player":"scavenger"},{"name":"A0BaBaGunTower","id":1058,"position":[10944,12864],"rotation":49152,"player":"scavenger"},{"name":"A0BaBaGunTowerEND","id":1059,"position":[10560,12736],"rotation":16384,"player":"scavenger"},{"name":"A0BaBaGunTower","id":1060,"position":[10560,12864],"rotation":32768,"player":"scavenger"},{"name":"A0BaBaHorizontalWall","id":1061,"position":[10688,12864],"rotation":32768,"player":"scavenger"},{"name":"A0BaBaHorizontalWall","id":1062,"position":[10816,12864],"rotation":32768,"player":"scavenger"},{"name":"A0BaBaFlameTower","id":1063,"position":[10688,12736],"rotation":32768,"player":"scavenger"},{"name":"A0CannonTower","id":1064,"position":[10816,12736],"rotation":32768,"player":"scavenger"},{"name":"A0BaBaBunker","id":1065,"position":[10304,12864],"rotation":32768,"player":"scavenger"},{"name":"A0BaBaRocketPit","id":1066,"position":[10304,12736],"rotation":32768,"player":"scavenger"},{"name":"A0BaBaRocketPitAT","id":1067,"position":[10304,12608],"rotation":32768,"player":"scavenger"},{"name":"A0BaBaMortarPit","id":1068,"position":[10688,12608],"rotation":32768,"player":"scavenger"},{"name":"A0BaBaMortarPit","id":1069,"position":[10816,12608],"rotation":32768,"player":"scavenger"},{"name":"A0BaBaGunTowerEND","id":1070,"position":[9536,12736],"rotation":49152,"player":"scavenger"},{"name":"A0BaBaGunTower","id":1071,"position":[9536,12864],"rotation":16384,"player":"scavenger"},{"name":"A0BaBaGunTowerEND","id":1072,"position":[9920,12736],"rotation":49152,"player":"scavenger"},{"name":"A0BaBaGunTower","id":1073,"position":[9920,12864],"rotation":0,"player":"scavenger"},{"name":"A0BaBaHorizontalWall","id":1074,"position":[9792,12864],"rotation":0,"player":"scavenger"},{"name":"A0BaBaHorizontalWall","id":1075,"position":[9664,12864],"rotation":0,"player":"scavenger"},{"name":"A0BaBaFlameTower","id":1076,"position":[9792,12736],"rotation":0,"player":"scavenger"},{"name":"A0CannonTower","id":1077,"position":[9664,12736],"rotation":0,"player":"scavenger"},{"name":"A0BaBaBunker","id":1078,"position":[10176,12864],"rotation":0,"player":"scavenger"},{"name":"A0BaBaRocketPit","id":1079,"position":[10176,12736],"rotation":0,"player":"scavenger"},{"name":"A0BaBaRocketPitAT","id":1080,"position":[10176,12608],"rotation":0,"player":"scavenger"},{"name":"A0BaBaMortarPit","id":1081,"position":[9792,12608],"rotation":0,"player":"scavenger"},{"name":"A0BaBaMortarPit","id":1082,"position":[9664,12608],"rotation":0,"player":"scavenger"},{"name":"A0BaBaBunker","id":1083,"position":[9280,12864],"rotation":32768,"player":"scavenger"},{"name":"A0BaBaRocketPit","id":1084,"position":[9280,12736],"rotation":32768,"player":"scavenger"},{"name":"A0BaBaRocketPitAT","id":1085,"position":[9280,12608],"rotation":32768,"player":"scavenger"},{"name":"A0BaBaPowerGenerator","id":1086,"position":[10816,10176],"rotation":32768,"player":"scavenger"},{"name":"Emplacement-Howitzer150","id":1087,"position":[10560,11328],"rotation":0,"player":"scavenger"},{"name":"Emplacement-Howitzer150","id":1088,"position":[10560,11200],"rotation":0,"player":"scavenger"},{"name":"Emplacement-Howitzer150","id":1089,"position":[10560,11072],"rotation":0,"player":"scavenger"},{"name":"Emplacement-Howitzer150","id":1090,"position":[10560,10944],"rotation":0,"player":"scavenger"},{"name":"Emplacement-Howitzer150","id":1091,"position":[10560,10816],"rotation":0,"player":"scavenger"},{"name":"Emplacement-Howitzer150","id":1092,"position":[10560,10688],"rotation":0,"player":"scavenger"},{"name":"Emplacement-Howitzer150","id":1093,"position":[10560,10560],"rotation":0,"player":"scavenger"},{"name":"Emplacement-Howitzer150","id":1094,"position":[9920,11328],"rotation":0,"player":"scavenger"},{"name":"Emplacement-Howitzer150","id":1095,"position":[9920,11200],"rotation":0,"player":"scavenger"},{"name":"Emplacement-Howitzer150","id":1096,"position":[9920,11072],"rotation":0,"player":"scavenger"},{"name":"Emplacement-Howitzer150","id":1097,"position":[9920,10944],"rotation":0,"player":"scavenger"},{"name":"Emplacement-Howitzer150","id":1098,"position":[9920,10816],"rotation":0,"player":"scavenger"},{"name":"P0-AASite-Laser","id":1099,"position":[10944,10560],"rotation":0,"player":"scavenger"},{"name":"P0-AASite-Laser","id":1100,"position":[10944,10944],"rotation":0,"player":"scavenger"},{"name":"P0-AASite-Laser","id":1101,"position":[10944,11328],"rotation":0,"player":"scavenger"},{"name":"P0-AASite-Laser","id":1102,"position":[10304,11840],"rotation":0,"player":"scavenger"},{"name":"P0-AASite-Laser","id":1103,"position":[10176,11840],"rotation":0,"player":"scavenger"},{"name":"P0-AASite-Laser","id":1104,"position":[9280,11840],"rotation":0,"player":"scavenger"},{"name":"Emplacement-Howitzer150","id":1105,"position":[9920,10688],"rotation":0,"player":"scavenger"},{"name":"Emplacement-Howitzer150","id":1106,"position":[9920,10560],"rotation":0,"player":"scavenger"},{"name":"AASite-QuadMg1","id":1107,"position":[10944,11840],"rotation":0,"player":"scavenger"},{"name":"AASite-QuadMg1","id":1108,"position":[10560,11840],"rotation":0,"player":"scavenger"},{"name":"AASite-QuadMg1","id":1109,"position":[9920,11840],"rotation":0,"player":"scavenger"},{"name":"AASite-QuadMg1","id":1110,"position":[9536,11840],"rotation":0,"player":"scavenger"},{"name":"A0BaBaFactory","id":1111,"position":[10880,11584],"rotation":0,"player":"scavenger"},{"name":"A0BaBaPowerGenerator","id":1112,"position":[10816,9664],"rotation":32768,"player":"scavenger"},{"name":"A0BaBaPowerGenerator","id":1113,"position":[10816,9920],"rotation":32768,"player":"scavenger"},{"name":"A0BaBaPowerGenerator","id":1114,"position":[10816,9408],"rotation":32768,"player":"scavenger"},{"name":"A0BaBaPowerGenerator","id":1115,"position":[10560,9792],"rotation":32768,"player":"scavenger"},{"name":"A0ResourceExtractor","id":1116,"position":[12224,704],"rotation":32768,"startpos":5},{"name":"A0ResourceExtractor","id":1117,"position":[11968,704],"rotation":32768,"startpos":5},{"name":"A0ResourceExtractor","id":1118,"position":[11840,576],"rotation":32768,"startpos":5},{"name":"A0ResourceExtractor","id":1119,"position":[11968,576],"rotation":32768,"startpos":5},{"name":"A0ResourceExtractor","id":1120,"position":[11840,704],"rotation":32768,"startpos":5},{"name":"A0ResourceExtractor","id":1121,"position":[11584,704],"rotation":32768,"startpos":5},{"name":"A0ResourceExtractor","id":1122,"position":[11584,576],"rotation":32768,"startpos":5},{"name":"A0ResourceExtractor","id":1123,"position":[11456,576],"rotation":32768,"startpos":5},{"name":"A0ResourceExtractor","id":1125,"position":[11200,576],"rotation":32768,"startpos":5},{"name":"A0ResourceExtractor","id":1126,"position":[11200,704],"rotation":32768,"startpos":5},{"name":"A0ResourceExtractor","id":1129,"position":[12352,704],"rotation":32768,"startpos":5},{"name":"A0ResourceExtractor","id":1127,"position":[13376,576],"rotation":32768,"startpos":5},{"name":"A0ResourceExtractor","id":1130,"position":[12608,704],"rotation":32768,"startpos":5},{"name":"A0ResourceExtractor","id":1132,"position":[13120,704],"rotation":32768,"startpos":5},{"name":"A0ResourceExtractor","id":1128,"position":[11072,704],"rotation":32768,"startpos":5},{"name":"A0ResourceExtractor","id":1134,"position":[10432,704],"rotation":32768,"startpos":5},{"name":"A0ResourceExtractor","id":1135,"position":[10816,704],"rotation":32768,"startpos":5},{"name":"A0ResourceExtractor","id":1133,"position":[13120,576],"rotation":32768,"startpos":5},{"name":"A0ResourceExtractor","id":1131,"position":[13376,704],"rotation":32768,"startpos":5},{"name":"A0ResourceExtractor","id":1138,"position":[13888,576],"rotation":32768,"startpos":5},{"name":"A0ResourceExtractor","id":1136,"position":[10816,576],"rotation":32768,"startpos":5},{"name":"A0ResourceExtractor","id":1139,"position":[13504,704],"rotation":32768,"startpos":5},{"name":"A0ResourceExtractor","id":1141,"position":[13760,704],"rotation":32768,"startpos":5},{"name":"A0ResourceExtractor","id":1140,"position":[10688,576],"rotation":32768,"startpos":5},{"name":"A0ResourceExtractor","id":1143,"position":[11072,576],"rotation":32768,"startpos":5},{"name":"A0ResourceExtractor","id":1144,"position":[10688,704],"rotation":32768,"startpos":5},{"name":"A0ResourceExtractor","id":1145,"position":[10304,704],"rotation":32768,"startpos":5},{"name":"A0ResourceExtractor","id":1137,"position":[12992,576],"rotation":32768,"startpos":5},{"name":"A0ResourceExtractor","id":1147,"position":[12736,704],"rotation":32768,"startpos":5},{"name":"A0ResourceExtractor","id":1148,"position":[12736,576],"rotation":32768,"startpos":5},{"name":"A0ResourceExtractor","id":1146,"position":[10304,576],"rotation":32768,"startpos":5},{"name":"A0ResourceExtractor","id":1149,"position":[12608,576],"rotation":32768,"startpos":5},{"name":"A0ResourceExtractor","id":1151,"position":[12352,576],"rotation":32768,"startpos":5},{"name":"A0ResourceExtractor","id":1142,"position":[13504,576],"rotation":32768,"startpos":5},{"name":"A0ResourceExtractor","id":1124,"position":[11456,704],"rotation":32768,"startpos":5},{"name":"A0ResourceExtractor","id":1154,"position":[12224,576],"rotation":32768,"startpos":5},{"name":"A0ResourceExtractor","id":1153,"position":[13760,576],"rotation":32768,"startpos":5},{"name":"Sys-CB-Tower01","id":1157,"position":[9920,8000],"rotation":32768,"player":"scavenger"},{"name":"Sys-CB-Tower01","id":1158,"position":[10560,8000],"rotation":32768,"player":"scavenger"},{"name":"Sys-SensoTowerWS","id":1159,"position":[9920,9280],"rotation":32768,"player":"scavenger"},{"name":"Sys-SensoTowerWS","id":1160,"position":[10560,9280],"rotation":32768,"player":"scavenger"},{"name":"P0-AASite-Laser","id":1161,"position":[9280,7744],"rotation":32768,"player":"scavenger"},{"name":"P0-AASite-Laser","id":1162,"position":[10176,7744],"rotation":32768,"player":"scavenger"},{"name":"P0-AASite-Laser","id":1163,"position":[10304,7744],"rotation":32768,"player":"scavenger"},{"name":"P0-AASite-Laser","id":1164,"position":[10944,9024],"rotation":32768,"player":"scavenger"},{"name":"P0-AASite-Laser","id":1165,"position":[10944,8640],"rotation":32768,"player":"scavenger"},{"name":"P0-AASite-Laser","id":1166,"position":[10944,8256],"rotation":32768,"player":"scavenger"},{"name":"A0ResourceExtractor","id":1167,"position":[13888,9920],"rotation":16384,"player":"scavenger"},{"name":"A0ResourceExtractor","id":1168,"position":[13888,10048],"rotation":16384,"player":"scavenger"},{"name":"A0ResourceExtractor","id":1169,"position":[13888,10176],"rotation":16384,"player":"scavenger"},{"name":"A0ResourceExtractor","id":1170,"position":[13888,10304],"rotation":16384,"player":"scavenger"},{"name":"A0ResourceExtractor","id":1171,"position":[13888,10432],"rotation":16384,"player":"scavenger"},{"name":"A0ResourceExtractor","id":1172,"position":[13888,10816],"rotation":16384,"player":"scavenger"},{"name":"A0ResourceExtractor","id":1173,"position":[13888,10688],"rotation":16384,"player":"scavenger"},{"name":"A0ResourceExtractor","id":1174,"position":[13888,10560],"rotation":16384,"player":"scavenger"},{"name":"A0ResourceExtractor","id":1175,"position":[13888,10944],"rotation":16384,"player":"scavenger"},{"name":"A0ResourceExtractor","id":1176,"position":[13888,11072],"rotation":16384,"player":"scavenger"},{"name":"A0ResourceExtractor","id":1177,"position":[13888,9664],"rotation":16384,"player":"scavenger"},{"name":"A0ResourceExtractor","id":1178,"position":[13888,9792],"rotation":16384,"player":"scavenger"},{"name":"A0ResourceExtractor","id":1179,"position":[13888,9536],"rotation":16384,"player":"scavenger"},{"name":"A0ResourceExtractor","id":1180,"position":[13888,9408],"rotation":16384,"player":"scavenger"},{"name":"A0ResourceExtractor","id":1181,"position":[13888,9280],"rotation":16384,"player":"scavenger"},{"name":"A0ResourceExtractor","id":1182,"position":[13888,9152],"rotation":16384,"player":"scavenger"},{"name":"A0ResourceExtractor","id":1183,"position":[13888,9024],"rotation":16384,"player":"scavenger"},{"name":"A0ResourceExtractor","id":1184,"position":[13888,8896],"rotation":16384,"player":"scavenger"},{"name":"A0ResourceExtractor","id":1185,"position":[13888,8768],"rotation":16384,"player":"scavenger"},{"name":"A0ResourceExtractor","id":1186,"position":[13888,8640],"rotation":16384,"player":"scavenger"},{"name":"A0ResourceExtractor","id":1187,"position":[13888,8512],"rotation":16384,"player":"scavenger"},{"name":"A0ResourceExtractor","id":931,"position":[13760,18880],"rotation":0,"startpos":0},{"name":"A0ResourceExtractor","id":946,"position":[12992,18880],"rotation":0,"startpos":0},{"name":"A0ResourceExtractor","id":1023,"position":[11200,19008],"rotation":0,"startpos":0},{"name":"A0ResourceExtractor","id":948,"position":[11584,19008],"rotation":0,"startpos":0},{"name":"A0CommandCentre","id":1155,"position":[12288,1024],"rotation":32768,"startpos":5},{"name":"A0ResourceExtractor","id":1152,"position":[12992,704],"rotation":32768,"startpos":5},{"name":"A0ResourceExtractor","id":1150,"position":[10432,576],"rotation":32768,"startpos":5},{"name":"A0ResourceExtractor","id":1156,"position":[13888,704],"rotation":32768,"startpos":5},{"name":"A0BaBaGunTowerEND","id":1406,"position":[7616,12736],"rotation":0,"player":"scavenger"},{"name":"A0BaBaGunTowerEND","id":1407,"position":[7360,12864],"rotation":32768,"player":"scavenger"},{"name":"A0BaBaFactory","id":1408,"position":[7424,10176],"rotation":32768,"player":"scavenger"},{"name":"A0BaBaFactory","id":1409,"position":[7424,9408],"rotation":32768,"player":"scavenger"},{"name":"AASite-QuadMg1","id":1410,"position":[7616,11840],"rotation":32768,"player":"scavenger"},{"name":"AASite-QuadMg1","id":1411,"position":[7360,11840],"rotation":32768,"player":"scavenger"},{"name":"A0BaBaFactory","id":1412,"position":[7424,11456],"rotation":32768,"player":"scavenger"},{"name":"A0BaBaHorizontalWall","id":1413,"position":[7488,12736],"rotation":0,"player":"scavenger"},{"name":"A0BaBaFlameTower","id":1414,"position":[7616,12608],"rotation":0,"player":"scavenger"},{"name":"A0CannonTower","id":1415,"position":[7360,12608],"rotation":0,"player":"scavenger"},{"name":"A0BaBaMortarPit","id":1416,"position":[7488,12608],"rotation":0,"player":"scavenger"},{"name":"A0BaBaGunTowerEND","id":1417,"position":[7360,12352],"rotation":32768,"player":"scavenger"},{"name":"A0BaBaGunTowerEND","id":1418,"position":[7616,12224],"rotation":0,"player":"scavenger"},{"name":"A0BaBaGunTowerEND","id":1419,"position":[7616,12352],"rotation":0,"player":"scavenger"},{"name":"A0BaBaGunTowerEND","id":1420,"position":[7360,12224],"rotation":32768,"player":"scavenger"},{"name":"A0BaBaHorizontalWall","id":1421,"position":[7488,12352],"rotation":0,"player":"scavenger"},{"name":"A0BaBaHorizontalWall","id":1422,"position":[7488,12224],"rotation":0,"player":"scavenger"},{"name":"A0BaBaHorizontalWall","id":1423,"position":[7488,6720],"rotation":32768,"player":"scavenger"},{"name":"A0BaBaGunTowerEND","id":1424,"position":[7616,7232],"rotation":0,"player":"scavenger"},{"name":"A0BaBaGunTowerEND","id":1425,"position":[7360,7232],"rotation":32768,"player":"scavenger"},{"name":"A0CannonTower","id":1426,"position":[7360,6976],"rotation":32768,"player":"scavenger"},{"name":"A0BaBaFactory","id":1427,"position":[7424,8128],"rotation":0,"player":"scavenger"},{"name":"A0CannonTower","id":1428,"position":[7360,7488],"rotation":32768,"player":"scavenger"},{"name":"A0BaBaFlameTower","id":1429,"position":[7616,7488],"rotation":32768,"player":"scavenger"},{"name":"A0BaBaMortarPit","id":1430,"position":[7488,7488],"rotation":32768,"player":"scavenger"},{"name":"A0BaBaFlameTower","id":1431,"position":[7616,6976],"rotation":32768,"player":"scavenger"},{"name":"A0BaBaHorizontalWall","id":1432,"position":[7488,7360],"rotation":32768,"player":"scavenger"},{"name":"A0BaBaHorizontalWall","id":1433,"position":[7488,7232],"rotation":32768,"player":"scavenger"},{"name":"A0BaBaMortarPit","id":1434,"position":[7488,6976],"rotation":32768,"player":"scavenger"},{"name":"A0BaBaHorizontalWall","id":1435,"position":[7488,6848],"rotation":32768,"player":"scavenger"},{"name":"A0BaBaGunTowerEND","id":1436,"position":[7616,6848],"rotation":0,"player":"scavenger"},{"name":"A0BaBaGunTowerEND","id":1437,"position":[7360,6848],"rotation":32768,"player":"scavenger"},{"name":"AASite-QuadMg1","id":1438,"position":[7360,7744],"rotation":32768,"player":"scavenger"},{"name":"AASite-QuadMg1","id":1439,"position":[7616,7744],"rotation":32768,"player":"scavenger"},{"name":"A0BaBaFlameTower","id":1440,"position":[7616,12096],"rotation":0,"player":"scavenger"},{"name":"A0CannonTower","id":1441,"position":[7360,12096],"rotation":0,"player":"scavenger"},{"name":"A0BaBaGunTowerEND","id":1442,"position":[7616,7360],"rotation":0,"player":"scavenger"},{"name":"A0BaBaGunTowerEND","id":1443,"position":[7360,7360],"rotation":32768,"player":"scavenger"},{"name":"A0BaBaGunTowerEND","id":1444,"position":[7360,6720],"rotation":32768,"player":"scavenger"},{"name":"A0BaBaGunTowerEND","id":1445,"position":[7616,6720],"rotation":0,"player":"scavenger"},{"name":"A0BaBaMortarPit","id":1446,"position":[7488,12096],"rotation":0,"player":"scavenger"},{"name":"A0BaBaHorizontalWall","id":1447,"position":[7488,12864],"rotation":0,"player":"scavenger"},{"name":"A0BaBaGunTowerEND","id":1448,"position":[7360,12736],"rotation":32768,"player":"scavenger"}]}